Workbook
Name advance_rate: Inputs!$B$22
Name avg_ticket_k: Inputs!$B$9
Name cof_apr: Scenarios!$B$9
Name disb_y1: Inputs!$B$6
Name disb_y2: Inputs!$B$7
Name disb_y3: Scenarios!$B$5
Name disb_y4: Inputs!$B$37
Name disb_y5: Inputs!$B$38
Name ead_bnpl: Risk!$C$7
Name ead_ext: Risk!$D$7
Name ead_pay30: Risk!$B$7
Name equity_pct: Inputs!$B$32
Name fee_bnpl_mo: Scenarios!$B$7
Name fee_ext_apr: Scenarios!$B$8
Name fee_pay30_mo: Scenarios!$B$6
Name lgd_bnpl: Risk!$C$6
Name lgd_ext: Risk!$D$6
Name lgd_pay30: Risk!$B$6
Name mix_bnpl: Inputs!$B$12
Name mix_ext: Inputs!$B$13
Name mix_pay30: Inputs!$B$11
Name opex_pct: Scenarios!$B$13
Name opex_y1_mult: Inputs!$B$34
Name opex_y2_mult: Inputs!$B$35
Name opex_y3_mult: Inputs!$B$36
Name opex_y4_mult: Inputs!$B$39
Name opex_y5_mult: Inputs!$B$40
Name pd_bnpl: Scenarios!$B$11
Name pd_ext: Scenarios!$B$12
Name pd_pay30: Scenarios!$B$10
Name tenor_bnpl: Inputs!$B$16
Name tenor_ext: Inputs!$B$17
Name tenor_pay30: Inputs!$B$15

Sheet Guide
A1: Mal · Product 1 · Smart Invoice
A2: Invoice Discount + BNPL embedded + Flexible Tenure embedded
A3: Currency: AED · Unit: M (millions) unless noted · Time: annualised
A6: Purpose | B6: Canonical financial model for Mal Smart Invoice. Source of truth for the prototype viewer in section-financial.jsx. Hand to Anthropic Model Builder / Valuation Reviewer agents in Claude.ai for stress-testing and scenario expansion.
A7: Structure | B7: Inputs (editable) → Volume & Mix → 3 track P&Ls (Pay-30, BNPL, Term Extension) → Combined → Unit Economics → Sensitivity → Validation. Each track P&L is identical in shape so agents can compare them.
A8: Editing | B8: Lilac cells = inputs (edit these). Paper cells = formulas (do not overwrite). Sage cells = key outputs. Named ranges defined for every input — see Formulas tab in Excel.
A10: UAE benchmarks used
A11: Cost of funds | B11: 3M EIBOR ~5.10–5.30% (May 2026). NBFI spread 1.0–1.5% over EIBOR for senior unsecured. Use 6.5%. Sources: CBUAE Monetary Bulletin Q1 2026; Fitch UAE Banks 2026 outlook.
A12: Discount fee (1.3%/mo) | B12: UAE SME factoring market: 1.5–3.0%/mo. Mashreq Trade, CBI Trade, ENBD Business Banking SCF: ~1.5–2.2%/mo. eFunder, Bridgr (UAE NBFC): 1.8–2.8%/mo. Mal at 1.3%/mo (15.6% APR) sits intentionally below market band — embedded-checkout convenience premium without consumer-style pricing on SME book. Source: FSRA NBFC pricing reviews; broker-dealer trade-finance schedules.
A13: BNPL fee (1.5%/mo) | B13: Consumer BNPL (Tabby/Tamara/Postpay): 3.0–3.5%/mo flat to merchant. B2B BNPL (Sympl, ToYou Pay Later): 2.0–2.8%/mo. Mal at 1.5%/mo (18% APR) reflects supplier-discount blend embedded in checkout flow vs standalone B2B BNPL. Tightened from 1.8% to keep headline RAROC defensible. Source: company T&Cs, MoF B2B BNPL guidelines 2025.
A14: Risk: PD×LGD×EAD framework | B14: Pay-30: PD 2.0%, LGD 25% (invoice collateral). BNPL: PD 4.0%, LGD 45%. Extension: PD 10.0%, LGD 65% (unsecured workout). EAD 100% (no undrawn). Net loss rate blended 2.6% on book. Source: Basel III IRB foundation; CBUAE FSR 2025 §3.4; Moody's UAE Banking 2026.
A15: Term extension (16% APR) | B15: Restructured/workout SME credit in UAE: 16–22% APR depending on collateral. CBUAE allows distressed-credit pricing up to consumer-protection caps. Note: 16% sits at low end — see Validation sheet for risk-priced alternative at 19%.
A16: OpEx (2.4% of book) | B16: Mature UAE factor: 1.5–2.5% of book. Early-stage fintech lender: 4–6% Y1 falling to 2–3% Y3. Mal trajectory plausible if scaling per disbursement plan. Source: NBFC public filings (Reem Finance, Aafaq); Strategy& UAE fintech benchmarks 2025.
A17: Equity (14% of book) | B17: CBUAE Capital Adequacy minimum: 10.5% CET1 + 2.5% conservation buffer = 13% Tier-1 standard. NBFCs: 10–15%. Mal at 14% adds 1-pt CRO management buffer above standard — 7.14× leverage vs 8.33× at 12% equity. Source: CBUAE Reg 32/2013 amended 2024; Basel III local implementation.
A18: Advance rate (90%) | B18: UAE invoice discount norm: 80–95% of face. 90% standard for prime obligor. Higher for anchor-validated invoices. Source: Mashreq SCF, CBI Working Capital schedules.
A19: Avg ticket (AED 80k) | B19: UAE SME invoice median 50–120k (DED registry data inferred). Mal target segment trade/services. Source: Strategy doc Section 4.2.
A20: Avg tenor (75 days) | B20: Blended: Pay-30 (40% mix), BNPL 60-180 (50% mix avg ~90d), Extension 6-mo (10% mix). Weighted = 75d.
A22: Last updated | B22: =TODAY() -> 46152
A23: Bench-marks NOT yet validated against Moody's | B23: Phase 2: replace defaultRatePct per track with PD/LGD/EAD curves from Moody's MCP for actual UAE private-company ratings distribution.

Sheet Dashboard
A1: Mal · Smart Invoice
A2: Live view of the canonical financial model. All figures recompute when Inputs / Risk Layer / Scenarios change.
B4: Y3 Disbursement | D4: Y3 Net Income | F4: Y3 RAROC (post-tax) | H4: Y1→Y5 Cum Net Income | J4: Y5 Equity Required
B5: =disb_y3 -> 4000 | D5: ='Combined P&L'!D35 -> 26.328419 | F5: ='Combined P&L'!D38 -> 23.111768 | H5: =SUM('Combined P&L'!B35:F35) -> 199.15311 | J5: ='Combined P&L'!F13 -> 370.23288
B6: AED M (face) | D6: AED M (post-tax) | F6: on equity | H6: AED M (post-tax 5-yr) | J6: AED M (Tier-1 base)
B27: Y3 Net Contribution sensitivity · Default rate × Cost of funds
B28: Live mirror of Sensitivity sheet · lilac = best, danger = worst
B30: =Sensitivity!A4 -> PD × → / COF ↓ | C30: =Sensitivity!B4 -> 0.6× PD | D30: =Sensitivity!C4 -> 0.8× PD | E30: =Sensitivity!D4 -> 1.0× PD | F30: =Sensitivity!E4 -> 1.2× PD | G30: =Sensitivity!F4 -> 1.5× PD | H30: =Sensitivity!G4 -> 1.8× PD | I30: =Sensitivity!H4 -> 2.2× PD
B31: =Sensitivity!A5 -> COF 5.5% | C31: =Sensitivity!B5 -> 62.779068 | D31: =Sensitivity!C5 -> 58.441315 | E31: =Sensitivity!D5 -> 54.103562 | F31: =Sensitivity!E5 -> 49.765808 | G31: =Sensitivity!F5 -> 43.259178 | H31: =Sensitivity!G5 -> 36.752548 | I31: =Sensitivity!H5 -> 28.077041
B32: =Sensitivity!A6 -> COF 6.0% | C32: =Sensitivity!B6 -> 58.710575 | D32: =Sensitivity!C6 -> 54.372822 | E32: =Sensitivity!D6 -> 50.035068 | F32: =Sensitivity!E6 -> 45.697315 | G32: =Sensitivity!F6 -> 39.190685 | H32: =Sensitivity!G6 -> 32.684055 | I32: =Sensitivity!H6 -> 24.008548
B33: =Sensitivity!A7 -> COF 6.5% | C33: =Sensitivity!B7 -> 54.642082 | D33: =Sensitivity!C7 -> 50.304329 | E33: =Sensitivity!D7 -> 45.966575 | F33: =Sensitivity!E7 -> 41.628822 | G33: =Sensitivity!F7 -> 35.122192 | H33: =Sensitivity!G7 -> 28.615562 | I33: =Sensitivity!H7 -> 19.940055
B34: =Sensitivity!A8 -> COF 7.0% | C34: =Sensitivity!B8 -> 50.573589 | D34: =Sensitivity!C8 -> 46.235836 | E34: =Sensitivity!D8 -> 41.898082 | F34: =Sensitivity!E8 -> 37.560329 | G34: =Sensitivity!F8 -> 31.053699 | H34: =Sensitivity!G8 -> 24.547068 | I34: =Sensitivity!H8 -> 15.871562
B35: =Sensitivity!A9 -> COF 7.5% | C35: =Sensitivity!B9 -> 46.505096 | D35: =Sensitivity!C9 -> 42.167342 | E35: =Sensitivity!D9 -> 37.829589 | F35: =Sensitivity!E9 -> 33.491836 | G35: =Sensitivity!F9 -> 26.985205 | H35: =Sensitivity!G9 -> 20.478575 | I35: =Sensitivity!H9 -> 11.803068
B36: =Sensitivity!A10 -> COF 8.0% | C36: =Sensitivity!B10 -> 42.436603 | D36: =Sensitivity!C10 -> 38.098849 | E36: =Sensitivity!D10 -> 33.761096 | F36: =Sensitivity!E10 -> 29.423342 | G36: =Sensitivity!F10 -> 22.916712 | H36: =Sensitivity!G10 -> 16.410082 | I36: =Sensitivity!H10 -> 7.7345753
B37: =Sensitivity!A11 -> COF 8.5% | C37: =Sensitivity!B11 -> 38.36811 | D37: =Sensitivity!C11 -> 34.030356 | E37: =Sensitivity!D11 -> 29.692603 | F37: =Sensitivity!E11 -> 25.354849 | G37: =Sensitivity!F11 -> 18.848219 | H37: =Sensitivity!G11 -> 12.341589 | I37: =Sensitivity!H11 -> 3.6660822
A40: Chart data (do not delete)
A42: Disbursement by track (AED M, face value)
A43: Track | B43: Y1 | C43: Y2 | D43: Y3 | E43: Y4 | F43: Y5
A44: Pay-30 | B44: ='Volume & Mix'!B5*mix_pay30/100 -> 100 | C44: ='Volume & Mix'!C5*mix_pay30/100 -> 600 | D44: ='Volume & Mix'!D5*mix_pay30/100 -> 1600 | E44: ='Volume & Mix'!E5*mix_pay30/100 -> 3200 | F44: ='Volume & Mix'!F5*mix_pay30/100 -> 5200
A45: BNPL | B45: ='Volume & Mix'!B5*mix_bnpl/100 -> 125 | C45: ='Volume & Mix'!C5*mix_bnpl/100 -> 750 | D45: ='Volume & Mix'!D5*mix_bnpl/100 -> 2000 | E45: ='Volume & Mix'!E5*mix_bnpl/100 -> 4000 | F45: ='Volume & Mix'!F5*mix_bnpl/100 -> 6500
A46: Term Extension | B46: ='Volume & Mix'!B5*mix_ext/100 -> 25 | C46: ='Volume & Mix'!C5*mix_ext/100 -> 150 | D46: ='Volume & Mix'!D5*mix_ext/100 -> 400 | E46: ='Volume & Mix'!E5*mix_ext/100 -> 800 | F46: ='Volume & Mix'!F5*mix_ext/100 -> 1300
A48: P&L margins (% of book)
A49: Metric | B49: Y1 | C49: Y2 | D49: Y3 | E49: Y4 | F49: Y5
A50: NIM % | B50: ='Combined P&L'!B16 -> 10.714545 | C50: ='Combined P&L'!C16 -> 10.714545 | D50: ='Combined P&L'!D16 -> 10.714545 | E50: ='Combined P&L'!E16 -> 10.714545 | F50: ='Combined P&L'!F16 -> 10.714545
A51: Loss rate % | B51: ='Combined P&L'!B17 -> 2.6654545 | C51: ='Combined P&L'!C17 -> 2.6654545 | D51: ='Combined P&L'!D17 -> 2.6654545 | E51: ='Combined P&L'!E17 -> 2.6654545 | F51: ='Combined P&L'!F17 -> 2.6654545
A52: OpEx % | B52: ='Combined P&L'!B18 -> 4.008 | C52: ='Combined P&L'!C18 -> 3 | D52: ='Combined P&L'!D18 -> 2.4 | E52: ='Combined P&L'!E18 -> 2.28 | F52: ='Combined P&L'!F18 -> 2.208
A53: Net margin % | B53: ='Combined P&L'!B19 -> 23.474863 | C53: ='Combined P&L'!C19 -> 29.330376 | D53: ='Combined P&L'!D19 -> 32.815801 | E53: ='Combined P&L'!E19 -> 33.512886 | F53: ='Combined P&L'!F19 -> 33.931136
A55: Returns (% / % on equity)
A56: Metric | B56: Y1 | C56: Y2 | D56: Y3 | E56: Y4 | F56: Y5
A57: ROA | B57: ='Combined P&L'!B20 -> 4.0410909 | C57: ='Combined P&L'!C20 -> 5.0490909 | D57: ='Combined P&L'!D20 -> 5.6490909 | E57: ='Combined P&L'!E20 -> 5.7690909 | F57: ='Combined P&L'!F20 -> 5.8410909
A58: RAROC | B58: ='Combined P&L'!B21 -> 28.864935 | C58: ='Combined P&L'!C21 -> 36.064935 | D58: ='Combined P&L'!D21 -> 40.350649 | E58: ='Combined P&L'!E21 -> 41.207792 | F58: ='Combined P&L'!F21 -> 41.722078

Sheet Inputs
A1: Inputs · Smart Invoice
A2: Edit lilac cells. Named ranges available — see formulas in track P&L sheets.
A4: Assumption | B4: Value | C4: Unit | E4: Named range | F4: Validation note
A5: Volume
A6: Disbursement Y1 | B6: 250 | C6: AED M | E6: disb_y1 | F6: Strategy doc Section 5.1 — Y1 plan.
A7: Disbursement Y2 | B7: 1500 | C7: AED M | E7: disb_y2 | F7: Strategy doc Section 5.1 — Y2 plan.
A8: Disbursement Y3 | B8: 4000 | C8: AED M | E8: disb_y3 | F8: Strategy doc Section 5.1 — Y3 plan.
A9: Avg ticket size | B9: 80 | C9: AED K | E9: avg_ticket_k | F9: UAE SME invoice median 50–120k.
A10: Mix
A11: Pay-30 share of book | B11: 40 | C11: % | E11: mix_pay30 | F11: Buyer plan picker default; demo flow data.
A12: BNPL share of book | B12: 50 | C12: % | E12: mix_bnpl | F12: Pay-60/90/120/180 plans blended.
A13: Term Extension share | B13: 10 | C13: % | E13: mix_ext | F13: Extension penetration ~22% × Pay-30 share.
A14: Tenor
A15: Pay-30 avg tenor | B15: 30 | C15: days | E15: tenor_pay30 | F15: Single-bullet 30-day pay.
A16: BNPL avg tenor | B16: 105 | C16: days | E16: tenor_bnpl | F16: Weighted avg of 60/90/120/180 plans.
A17: Term Extension tenor | B17: 180 | C17: days | E17: tenor_ext | F17: 6-month restructure schedule.
A18: Pricing
A19: Pay-30 discount fee | B19: 1.3 | C19: % per month | E19: fee_pay30_mo | F19: Tightened from 1.6 — prevents consumer-style pricing on SME book. Mashreq SCF / CBI Trade band 1.5-2.2%/mo; Mal floors below band on embedded-checkout convenience premium.
A20: BNPL fee | B20: 1.5 | C20: % per month | E20: fee_bnpl_mo | F20: Tightened from 1.8 — B2B BNPL UAE band 2.0-2.8%/mo; 1.5% reflects supplier-discount blend, embedded-platform play.
A21: Term Extension APR | B21: 16 | C21: % | E21: fee_ext_apr | F21: 16% low end. See Validation for 19% risk-priced alt.
A22: Advance rate | B22: 90 | C22: % of invoice | E22: advance_rate | F22: UAE norm 80–95%; 90% prime obligor.
A23: Cost
A24: Cost of funds | B24: 6.5 | C24: % APR | E24: cof_apr | F24: EIBOR ~5.2% + NBFI spread 1.3% = 6.5%.
A25: OpEx (% of avg book) | B25: 2.4 | C25: % | E25: opex_pct | F25: Y3 mature; ramps 4.0/3.0/2.4 per JSX.
A26: Risk
A27: Pay-30 net loss rate (display) | B27: =Risk!B9 -> 0.7 | C27: % of book | E27: (display only) | F27: Derived: PD×LGD×EAD. Authoritative source = Risk Layer.
A28: BNPL net loss rate (display) | B28: =Risk!C9 -> 1.8 | C28: % of book | E28: (display only) | F28: Derived: PD×LGD×EAD. Authoritative source = Risk Layer.
A29: Term Extension net loss rate (display) | B29: =Risk!D9 -> 6.5 | C29: % of book | E29: (display only) | F29: Derived: PD×LGD×EAD. Authoritative source = Risk Layer.
A30: (deprecated — was "Recovery %") | F30: Replaced by per-track LGDs on Risk Layer (25/45/65). Row kept as audit trail.
A31: Capital
A32: Equity (% of avg book) | B32: 14 | C32: % | E32: equity_pct | F32: Tightened from 12% — CBUAE Tier-1 floor 10.5% CET1 + 2.5% conservation = 13% standard; Mal at 14% adds 1-pt CRO management buffer.
A33: OpEx ramp
A34: OpEx Y1 multiplier | B34: 1.67 | C34: x of base | E34: opex_y1_mult | F34: Y1 = 4.0% / 2.4% = 1.67x.
A35: OpEx Y2 multiplier | B35: 1.25 | C35: x of base | E35: opex_y2_mult | F35: Y2 = 3.0% / 2.4% = 1.25x.
A36: OpEx Y3 multiplier | B36: 1 | C36: x of base | E36: opex_y3_mult | F36: Y3 = 2.4% (mature).
A37: Disbursement Y4 | B37: 8000 | C37: AED M | E37: disb_y4 | F37: Five-year extension; growth tapering from Y3 trajectory.
A38: Disbursement Y5 | B38: 13000 | C38: AED M | E38: disb_y5 | F38: Five-year extension; mature scale assumption.
A39: OpEx Y4 multiplier | B39: 0.95 | C39: x of base | E39: opex_y4_mult | F39: Y4 = 2.4% × 0.95 = 2.28% — operating leverage.
A40: OpEx Y5 multiplier | B40: 0.92 | C40: x of base | E40: opex_y5_mult | F40: Y5 = 2.4% × 0.92 = 2.21% — continued leverage.

Sheet Volume & Mix
A1: Volume & Average Book per Track
A2: book = disbursement × advance_rate × tenor / 365 × mix_share
A4: Item | B4: Y1 | C4: Y2 | D4: Y3 | E4: Y4 | F4: Y5 | H4: Notes
A5: Disbursement (face value) | B5: =disb_y1 -> 250 | C5: =disb_y2 -> 1500 | D5: =disb_y3 -> 4000 | E5: =disb_y4 -> 8000 | F5: =disb_y5 -> 13000 | H5: AED M
A6: Advanced principal | B6: =disb_y1*advance_rate/100 -> 225 | C6: =disb_y2*advance_rate/100 -> 1350 | D6: =disb_y3*advance_rate/100 -> 3600 | E6: =disb_y4*advance_rate/100 -> 7200 | F6: =disb_y5*advance_rate/100 -> 11700 | H6: disb × advance_rate
A8: Per-track average book (AED M)
A9: Pay-30 book | B9: =disb_y1*advance_rate/100*tenor_pay30/365*mix_pay30/100 -> 7.3972603 | C9: =disb_y2*advance_rate/100*tenor_pay30/365*mix_pay30/100 -> 44.383562 | D9: =disb_y3*advance_rate/100*tenor_pay30/365*mix_pay30/100 -> 118.35616 | E9: =disb_y4*advance_rate/100*tenor_pay30/365*mix_pay30/100 -> 236.71233 | F9: =disb_y5*advance_rate/100*tenor_pay30/365*mix_pay30/100 -> 384.65753 | H9: mix_pay30 share, 30-day tenor
A10: BNPL book | B10: =disb_y1*advance_rate/100*tenor_bnpl/365*mix_bnpl/100 -> 32.363014 | C10: =disb_y2*advance_rate/100*tenor_bnpl/365*mix_bnpl/100 -> 194.17808 | D10: =disb_y3*advance_rate/100*tenor_bnpl/365*mix_bnpl/100 -> 517.80822 | E10: =disb_y4*advance_rate/100*tenor_bnpl/365*mix_bnpl/100 -> 1035.6164 | F10: =disb_y5*advance_rate/100*tenor_bnpl/365*mix_bnpl/100 -> 1682.8767 | H10: mix_bnpl share, 105-day blended tenor
A11: Term Extension book | B11: =disb_y1*advance_rate/100*tenor_ext/365*mix_ext/100 -> 11.09589 | C11: =disb_y2*advance_rate/100*tenor_ext/365*mix_ext/100 -> 66.575342 | D11: =disb_y3*advance_rate/100*tenor_ext/365*mix_ext/100 -> 177.53425 | E11: =disb_y4*advance_rate/100*tenor_ext/365*mix_ext/100 -> 355.06849 | F11: =disb_y5*advance_rate/100*tenor_ext/365*mix_ext/100 -> 576.9863 | H11: mix_ext share, 180-day tenor
A13: Total avg book | B13: =SUM(B9:B11) -> 50.856164 | C13: =SUM(C9:C11) -> 305.13699 | D13: =SUM(D9:D11) -> 813.69863 | E13: =SUM(E9:E11) -> 1627.3973 | F13: =SUM(F9:F11) -> 2644.5205 | H13: sum of tracks

Sheet Disbursement Plan
A1: Disbursement Plan · 5-year trajectory
A2: Strategy doc Sections 5.1 — figures locked unless flagged. Sourced from disb_y1..disb_y5.
A4: Line (AED M) | B4: Y1 | C4: Y2 | D4: Y3 | E4: Y4 | F4: Y5 | G4: Y1→Y5 CAGR | H4: Notes
A5: Disbursement (face) | B5: =disb_y1 -> 250 | C5: =disb_y2 -> 1500 | D5: =disb_y3 -> 4000 | E5: =disb_y4 -> 8000 | F5: =disb_y5 -> 13000 | G5: =(F5/B5)^(1/4)-1 -> 1.6853496 | H5: AED M invoice face value disbursed
A6: YoY growth | C6: =C5/B5-1 -> 5 | D6: =D5/C5-1 -> 1.6666667 | E6: =E5/D5-1 -> 1 | F6: =F5/E5-1 -> 0.625 | H6: Strategy: 6.0x → 2.7x → 2.0x → 1.6x ramp
A8: Advanced principal | B8: =B5*advance_rate/100 -> 225 | C8: =C5*advance_rate/100 -> 1350 | D8: =D5*advance_rate/100 -> 3600 | E8: =E5*advance_rate/100 -> 7200 | F8: =F5*advance_rate/100 -> 11700 | G8: =(F8/B8)^(1/4)-1 -> 1.6853496 | H8: = face × advance_rate (90%)
A10: Total avg book | B10: ='Volume & Mix'!B13 -> 50.856164 | C10: ='Volume & Mix'!C13 -> 305.13699 | D10: ='Volume & Mix'!D13 -> 813.69863 | E10: ='Volume & Mix'!E13 -> 1627.3973 | F10: ='Volume & Mix'!F13 -> 2644.5205 | G10: =(F10/B10)^(1/4)-1 -> 1.6853496 | H10: Weighted by mix × tenor
A12: Composition (% of book)
A13: Pay-30 share | B13: ='Volume & Mix'!B9/'Volume & Mix'!B13 -> 0.14545455 | C13: ='Volume & Mix'!C9/'Volume & Mix'!C13 -> 0.14545455 | D13: ='Volume & Mix'!D9/'Volume & Mix'!D13 -> 0.14545455 | E13: ='Volume & Mix'!E9/'Volume & Mix'!E13 -> 0.14545455 | F13: ='Volume & Mix'!F9/'Volume & Mix'!F13 -> 0.14545455 | H13: 30-day tenor weight is small in book share
A14: BNPL share | B14: ='Volume & Mix'!B10/'Volume & Mix'!B13 -> 0.63636364 | C14: ='Volume & Mix'!C10/'Volume & Mix'!C13 -> 0.63636364 | D14: ='Volume & Mix'!D10/'Volume & Mix'!D13 -> 0.63636364 | E14: ='Volume & Mix'!E10/'Volume & Mix'!E13 -> 0.63636364 | F14: ='Volume & Mix'!F10/'Volume & Mix'!F13 -> 0.63636364 | H14: Dominant book share — 105d tenor + 50% mix
A15: Term Extension share | B15: ='Volume & Mix'!B11/'Volume & Mix'!B13 -> 0.21818182 | C15: ='Volume & Mix'!C11/'Volume & Mix'!C13 -> 0.21818182 | D15: ='Volume & Mix'!D11/'Volume & Mix'!D13 -> 0.21818182 | E15: ='Volume & Mix'!E11/'Volume & Mix'!E13 -> 0.21818182 | F15: ='Volume & Mix'!F11/'Volume & Mix'!F13 -> 0.21818182 | H15: 180d distressed tenor

Sheet Risk
A1: Risk Layer · PD / LGD / EAD by Track
A2: Basel III IRB Foundation framework. EL = PD × LGD × EAD × book. Sources: Moody's UAE Banking 2026, CBUAE FSR 2025 §3.4, Basel III IRB.
A4: Parameter | B4: Pay-30 | C4: BNPL | D4: Term Extension | E4: Stress (1.5× PD) | F4: Source / Note
A5: PD (% p.a.) | B5: 2 | C5: 4 | D5: 10 | E5: =B5*1.5 -> 3 | F5: Stress = base PD × 1.5 (CBUAE 2020 COVID-19 downturn template)
A6: LGD (%) | B6: 35 | C6: 45 | D6: 65 | E6: (unchanged) | F6: LGD held flat under PD stress; downturn-LGD test in Scenarios
A7: EAD (% of book) | B7: 100 | C7: 100 | D7: 100 | E7: (unchanged) | F7: Phase 2: introduce CCF-based EAD if a revolving facility variant is launched
A9: Net loss rate (% of book) | B9: =B5*B6/100*B7/100 -> 0.7 | C9: =C5*C6/100*C7/100 -> 1.8 | D9: =D5*D6/100*D7/100 -> 6.5 | E9: see stress block below | F9: = PD×LGD×EAD (annualised, % of avg book)
A10: Stressed net loss rate (1.5× PD) | B10: =E5*B6/100*B7/100 -> 1.05 | C10: =C5*1.5*C6/100*C7/100 -> 2.7 | D10: =D5*1.5*D6/100*D7/100 -> 9.75 | F10: Stress = PD × 1.5; LGD/EAD held

Sheet Track A · Pay-30
A1: Track A · Pay-30 (single-bullet)
A2: Single-bullet 30-day pay. Invoice acts as collateral. Lowest default; lowest yield.
A4: Line | B4: Y1 | C4: Y2 | D4: Y3 | E4: Y4 | F4: Y5 | H4: Formula
A5: Avg book | B5: ='Volume & Mix'!B9 -> 7.3972603 | C5: ='Volume & Mix'!C9 -> 44.383562 | D5: ='Volume & Mix'!D9 -> 118.35616 | E5: ='Volume & Mix'!E9 -> 236.71233 | F5: ='Volume & Mix'!F9 -> 384.65753 | H5: from 'Volume & Mix'
A6: Gross yield (% APR) | B6: =fee_pay30_mo*12 -> 15.6 | C6: =fee_pay30_mo*12 -> 15.6 | D6: =fee_pay30_mo*12 -> 15.6 | E6: =fee_pay30_mo*12 -> 15.6 | F6: =fee_pay30_mo*12 -> 15.6 | H6: fee_pay30_mo × 12 = APR
A7: Gross interest income (AED M) | B7: =B5*B6/100 -> 1.1539726 | C7: =C5*C6/100 -> 6.9238356 | D7: =D5*D6/100 -> 18.463562 | E7: =E5*E6/100 -> 36.927123 | F7: =F5*F6/100 -> 60.006575 | H7: book × yield
A9: Cost of funds (% APR) | B9: =cof_apr -> 6.5 | C9: =cof_apr -> 6.5 | D9: =cof_apr -> 6.5 | E9: =cof_apr -> 6.5 | F9: =cof_apr -> 6.5
A10: Funding cost (AED M) | B10: =B5*B9/100 -> 0.48082192 | C10: =C5*C9/100 -> 2.8849315 | D10: =D5*D9/100 -> 7.6931507 | E10: =E5*E9/100 -> 15.386301 | F10: =F5*F9/100 -> 25.00274 | H10: book × COF
A12: NIM (AED M) | B12: =B7-B10 -> 0.67315068 | C12: =C7-C10 -> 4.0389041 | D12: =D7-D10 -> 10.770411 | E12: =E7-E10 -> 21.540822 | F12: =F7-F10 -> 35.003836 | H12: gross - funding
A14: PD (% APR) — pd_pay30 | B14: =pd_pay30 -> 2 | C14: =pd_pay30 -> 2 | D14: =pd_pay30 -> 2 | E14: =pd_pay30 -> 2 | F14: =pd_pay30 -> 2 | H14: Probability of default — Risk Layer sheet
A15: LGD (%) — lgd_pay30 | B15: =lgd_pay30 -> 35 | C15: =lgd_pay30 -> 35 | D15: =lgd_pay30 -> 35 | E15: =lgd_pay30 -> 35 | F15: =lgd_pay30 -> 35 | H15: Loss given default — collateral-implied
A16: Net loss rate (% of book) | B16: =B14*B15/100*ead_pay30/100 -> 0.7 | C16: =C14*C15/100*ead_pay30/100 -> 0.7 | D16: =D14*D15/100*ead_pay30/100 -> 0.7 | E16: =E14*E15/100*ead_pay30/100 -> 0.7 | F16: =F14*F15/100*ead_pay30/100 -> 0.7 | H16: PD × LGD × EAD
A17: Loss provision (AED M) | B17: =B5*B16/100 -> 0.051780822 | C17: =C5*C16/100 -> 0.31068493 | D17: =D5*D16/100 -> 0.82849315 | E17: =E5*E16/100 -> 1.6569863 | F17: =F5*F16/100 -> 2.6926027 | H17: book × net loss rate
A19: Risk-adj margin (AED M) | B19: =B12-B17 -> 0.62136986 | C19: =C12-C17 -> 3.7282192 | D19: =D12-D17 -> 9.9419178 | E19: =E12-E17 -> 19.883836 | F19: =F12-F17 -> 32.311233 | H19: NIM - losses
A21: OpEx % of book (Y1–Y5 ramp) | B21: =opex_pct*opex_y1_mult -> 4.008 | C21: =opex_pct*opex_y2_mult -> 3 | D21: =opex_pct*opex_y3_mult -> 2.4 | E21: =opex_pct*opex_y4_mult -> 2.28 | F21: =opex_pct*opex_y5_mult -> 2.208 | H21: ramps to mature in Y3
A22: OpEx (AED M) | B22: =B5*B21/100 -> 0.29648219 | C22: =C5*C21/100 -> 1.3315068 | D22: =D5*D21/100 -> 2.8405479 | E22: =E5*E21/100 -> 5.3970411 | F22: =F5*F21/100 -> 8.4932384 | H22: book × opex%
A24: Net contribution (AED M) | B24: =B19-B22 -> 0.32488767 | C24: =C19-C22 -> 2.3967123 | D24: =D19-D22 -> 7.1013699 | E24: =E19-E22 -> 14.486795 | F24: =F19-F22 -> 23.817995 | H24: RAM - OpEx
A25: ROA (% of avg book) | B25: =B24/B5*100 -> 4.392 | C25: =C24/C5*100 -> 5.4 | D25: =D24/D5*100 -> 6 | E25: =E24/E5*100 -> 6.12 | F25: =F24/F5*100 -> 6.192 | H25: net contrib / book
A27: Equity allocated (AED M) | B27: =B5*equity_pct/100 -> 1.0356164 | C27: =C5*equity_pct/100 -> 6.2136986 | D27: =D5*equity_pct/100 -> 16.569863 | E27: =E5*equity_pct/100 -> 33.139726 | F27: =F5*equity_pct/100 -> 53.852055 | H27: book × equity_pct
A28: RAROC (% on equity) | B28: =IF(B27>0,B24/B27*100,0) -> 31.371429 | C28: =IF(C27>0,C24/C27*100,0) -> 38.571429 | D28: =IF(D27>0,D24/D27*100,0) -> 42.857143 | E28: =IF(E27>0,E24/E27*100,0) -> 43.714286 | F28: =IF(F27>0,F24/F27*100,0) -> 44.228571 | H28: net contrib / equity

Sheet Track B · BNPL
A1: Track B · BNPL (60/90/120/180 blended)
A2: Multi-installment over 60–180 days. Higher exposure → higher default. Yield priced ~12.5% above Pay-30.
A4: Line | B4: Y1 | C4: Y2 | D4: Y3 | E4: Y4 | F4: Y5 | H4: Formula
A5: Avg book | B5: ='Volume & Mix'!B10 -> 32.363014 | C5: ='Volume & Mix'!C10 -> 194.17808 | D5: ='Volume & Mix'!D10 -> 517.80822 | E5: ='Volume & Mix'!E10 -> 1035.6164 | F5: ='Volume & Mix'!F10 -> 1682.8767 | H5: from 'Volume & Mix'
A6: Gross yield (% APR) | B6: =fee_bnpl_mo*12 -> 18 | C6: =fee_bnpl_mo*12 -> 18 | D6: =fee_bnpl_mo*12 -> 18 | E6: =fee_bnpl_mo*12 -> 18 | F6: =fee_bnpl_mo*12 -> 18 | H6: fee_bnpl_mo × 12 = APR
A7: Gross interest income (AED M) | B7: =B5*B6/100 -> 5.8253425 | C7: =C5*C6/100 -> 34.952055 | D7: =D5*D6/100 -> 93.205479 | E7: =E5*E6/100 -> 186.41096 | F7: =F5*F6/100 -> 302.91781 | H7: book × yield
A9: Cost of funds (% APR) | B9: =cof_apr -> 6.5 | C9: =cof_apr -> 6.5 | D9: =cof_apr -> 6.5 | E9: =cof_apr -> 6.5 | F9: =cof_apr -> 6.5
A10: Funding cost (AED M) | B10: =B5*B9/100 -> 2.1035959 | C10: =C5*C9/100 -> 12.621575 | D10: =D5*D9/100 -> 33.657534 | E10: =E5*E9/100 -> 67.315068 | F10: =F5*F9/100 -> 109.38699 | H10: book × COF
A12: NIM (AED M) | B12: =B7-B10 -> 3.7217466 | C12: =C7-C10 -> 22.330479 | D12: =D7-D10 -> 59.547945 | E12: =E7-E10 -> 119.09589 | F12: =F7-F10 -> 193.53082 | H12: gross - funding
A14: PD (% APR) — pd_bnpl | B14: =pd_bnpl -> 4 | C14: =pd_bnpl -> 4 | D14: =pd_bnpl -> 4 | E14: =pd_bnpl -> 4 | F14: =pd_bnpl -> 4 | H14: Probability of default — Risk Layer sheet
A15: LGD (%) — lgd_bnpl | B15: =lgd_bnpl -> 45 | C15: =lgd_bnpl -> 45 | D15: =lgd_bnpl -> 45 | E15: =lgd_bnpl -> 45 | F15: =lgd_bnpl -> 45 | H15: Loss given default — multi-installment
A16: Net loss rate (% of book) | B16: =B14*B15/100*ead_bnpl/100 -> 1.8 | C16: =C14*C15/100*ead_bnpl/100 -> 1.8 | D16: =D14*D15/100*ead_bnpl/100 -> 1.8 | E16: =E14*E15/100*ead_bnpl/100 -> 1.8 | F16: =F14*F15/100*ead_bnpl/100 -> 1.8 | H16: PD × LGD × EAD
A17: Loss provision (AED M) | B17: =B5*B16/100 -> 0.58253425 | C17: =C5*C16/100 -> 3.4952055 | D17: =D5*D16/100 -> 9.3205479 | E17: =E5*E16/100 -> 18.641096 | F17: =F5*F16/100 -> 30.291781 | H17: book × net loss rate
A19: Risk-adj margin (AED M) | B19: =B12-B17 -> 3.1392123 | C19: =C12-C17 -> 18.835274 | D19: =D12-D17 -> 50.227397 | E19: =E12-E17 -> 100.45479 | F19: =F12-F17 -> 163.23904 | H19: NIM - losses
A21: OpEx % of book (Y1–Y5 ramp) | B21: =opex_pct*opex_y1_mult -> 4.008 | C21: =opex_pct*opex_y2_mult -> 3 | D21: =opex_pct*opex_y3_mult -> 2.4 | E21: =opex_pct*opex_y4_mult -> 2.28 | F21: =opex_pct*opex_y5_mult -> 2.208 | H21: ramps to mature in Y3
A22: OpEx (AED M) | B22: =B5*B21/100 -> 1.2971096 | C22: =C5*C21/100 -> 5.8253425 | D22: =D5*D21/100 -> 12.427397 | E22: =E5*E21/100 -> 23.612055 | F22: =F5*F21/100 -> 37.157918 | H22: book × opex%
A24: Net contribution (AED M) | B24: =B19-B22 -> 1.8421027 | C24: =C19-C22 -> 13.009932 | D24: =D19-D22 -> 37.8 | E24: =E19-E22 -> 76.84274 | F24: =F19-F22 -> 126.08112 | H24: RAM - OpEx
A25: ROA (% of avg book) | B25: =B24/B5*100 -> 5.692 | C25: =C24/C5*100 -> 6.7 | D25: =D24/D5*100 -> 7.3 | E25: =E24/E5*100 -> 7.42 | F25: =F24/F5*100 -> 7.492 | H25: net contrib / book
A27: Equity allocated (AED M) | B27: =B5*equity_pct/100 -> 4.5308219 | C27: =C5*equity_pct/100 -> 27.184932 | D27: =D5*equity_pct/100 -> 72.493151 | E27: =E5*equity_pct/100 -> 144.9863 | F27: =F5*equity_pct/100 -> 235.60274 | H27: book × equity_pct
A28: RAROC (% on equity) | B28: =IF(B27>0,B24/B27*100,0) -> 40.657143 | C28: =IF(C27>0,C24/C27*100,0) -> 47.857143 | D28: =IF(D27>0,D24/D27*100,0) -> 52.142857 | E28: =IF(E27>0,E24/E27*100,0) -> 53 | F28: =IF(F27>0,F24/F27*100,0) -> 53.514286 | H28: net contrib / equity

Sheet Track C · Extension
A1: Track C · Term Extension (6-mo restructure)
A2: Workout product for Pay-30/BNPL non-payers. APR-priced. Distressed cohort: highest default; recovery lower.
A4: Line | B4: Y1 | C4: Y2 | D4: Y3 | E4: Y4 | F4: Y5 | H4: Formula
A5: Avg book | B5: ='Volume & Mix'!B11 -> 11.09589 | C5: ='Volume & Mix'!C11 -> 66.575342 | D5: ='Volume & Mix'!D11 -> 177.53425 | E5: ='Volume & Mix'!E11 -> 355.06849 | F5: ='Volume & Mix'!F11 -> 576.9863 | H5: from 'Volume & Mix'
A6: Gross yield (% APR) | B6: =fee_ext_apr -> 16 | C6: =fee_ext_apr -> 16 | D6: =fee_ext_apr -> 16 | E6: =fee_ext_apr -> 16 | F6: =fee_ext_apr -> 16 | H6: fee_ext_apr (direct APR)
A7: Gross interest income (AED M) | B7: =B5*B6/100 -> 1.7753425 | C7: =C5*C6/100 -> 10.652055 | D7: =D5*D6/100 -> 28.405479 | E7: =E5*E6/100 -> 56.810959 | F7: =F5*F6/100 -> 92.317808 | H7: book × yield
A9: Cost of funds (% APR) | B9: =cof_apr -> 6.5 | C9: =cof_apr -> 6.5 | D9: =cof_apr -> 6.5 | E9: =cof_apr -> 6.5 | F9: =cof_apr -> 6.5
A10: Funding cost (AED M) | B10: =B5*B9/100 -> 0.72123288 | C10: =C5*C9/100 -> 4.3273973 | D10: =D5*D9/100 -> 11.539726 | E10: =E5*E9/100 -> 23.079452 | F10: =F5*F9/100 -> 37.50411 | H10: book × COF
A12: NIM (AED M) | B12: =B7-B10 -> 1.0541096 | C12: =C7-C10 -> 6.3246575 | D12: =D7-D10 -> 16.865753 | E12: =E7-E10 -> 33.731507 | F12: =F7-F10 -> 54.813699 | H12: gross - funding
A14: PD (% APR) — pd_ext | B14: =pd_ext -> 10 | C14: =pd_ext -> 10 | D14: =pd_ext -> 10 | E14: =pd_ext -> 10 | F14: =pd_ext -> 10 | H14: Probability of default — Risk Layer sheet
A15: LGD (%) — lgd_ext | B15: =lgd_ext -> 65 | C15: =lgd_ext -> 65 | D15: =lgd_ext -> 65 | E15: =lgd_ext -> 65 | F15: =lgd_ext -> 65 | H15: Loss given default — workout/distressed
A16: Net loss rate (% of book) | B16: =B14*B15/100*ead_ext/100 -> 6.5 | C16: =C14*C15/100*ead_ext/100 -> 6.5 | D16: =D14*D15/100*ead_ext/100 -> 6.5 | E16: =E14*E15/100*ead_ext/100 -> 6.5 | F16: =F14*F15/100*ead_ext/100 -> 6.5 | H16: PD × LGD × EAD
A17: Loss provision (AED M) | B17: =B5*B16/100 -> 0.72123288 | C17: =C5*C16/100 -> 4.3273973 | D17: =D5*D16/100 -> 11.539726 | E17: =E5*E16/100 -> 23.079452 | F17: =F5*F16/100 -> 37.50411 | H17: book × net loss rate
A19: Risk-adj margin (AED M) | B19: =B12-B17 -> 0.33287671 | C19: =C12-C17 -> 1.9972603 | D19: =D12-D17 -> 5.3260274 | E19: =E12-E17 -> 10.652055 | F19: =F12-F17 -> 17.309589 | H19: NIM - losses
A21: OpEx % of book (Y1–Y5 ramp) | B21: =opex_pct*opex_y1_mult -> 4.008 | C21: =opex_pct*opex_y2_mult -> 3 | D21: =opex_pct*opex_y3_mult -> 2.4 | E21: =opex_pct*opex_y4_mult -> 2.28 | F21: =opex_pct*opex_y5_mult -> 2.208 | H21: ramps to mature in Y3
A22: OpEx (AED M) | B22: =B5*B21/100 -> 0.44472329 | C22: =C5*C21/100 -> 1.9972603 | D22: =D5*D21/100 -> 4.2608219 | E22: =E5*E21/100 -> 8.0955616 | F22: =F5*F21/100 -> 12.739858 | H22: book × opex%
A24: Net contribution (AED M) | B24: =B19-B22 -> -0.11184658 | C24: =C19-C22 -> 0 | D24: =D19-D22 -> 1.0652055 | E24: =E19-E22 -> 2.5564932 | F24: =F19-F22 -> 4.5697315 | H24: RAM - OpEx
A25: ROA (% of avg book) | B25: =B24/B5*100 -> -1.008 | C25: =C24/C5*100 -> 0 | D25: =D24/D5*100 -> 0.6 | E25: =E24/E5*100 -> 0.72 | F25: =F24/F5*100 -> 0.792 | H25: net contrib / book
A27: Equity allocated (AED M) | B27: =B5*equity_pct/100 -> 1.5534247 | C27: =C5*equity_pct/100 -> 9.3205479 | D27: =D5*equity_pct/100 -> 24.854795 | E27: =E5*equity_pct/100 -> 49.709589 | F27: =F5*equity_pct/100 -> 80.778082 | H27: book × equity_pct
A28: RAROC (% on equity) | B28: =IF(B27>0,B24/B27*100,0) -> -7.2 | C28: =IF(C27>0,C24/C27*100,0) -> 0 | D28: =IF(D27>0,D24/D27*100,0) -> 4.2857143 | E28: =IF(E27>0,E24/E27*100,0) -> 5.1428571 | F28: =IF(F27>0,F24/F27*100,0) -> 5.6571429 | H28: net contrib / equity

Sheet Combined P&L
A1: Combined Smart Invoice P&L
A2: Track A + Track B + Track C, five-year roll-up (Y1–Y5)
A4: Line (AED M) | B4: Y1 | C4: Y2 | D4: Y3 | E4: Y4 | F4: Y5
A5: Avg book | B5: ='Track A · Pay-30'!B5+'Track B · BNPL'!B5+'Track C · Extension'!B5 -> 50.856164 | C5: ='Track A · Pay-30'!C5+'Track B · BNPL'!C5+'Track C · Extension'!C5 -> 305.13699 | D5: ='Track A · Pay-30'!D5+'Track B · BNPL'!D5+'Track C · Extension'!D5 -> 813.69863 | E5: ='Track A · Pay-30'!E5+'Track B · BNPL'!E5+'Track C · Extension'!E5 -> 1627.3973 | F5: ='Track A · Pay-30'!F5+'Track B · BNPL'!F5+'Track C · Extension'!F5 -> 2644.5205
A6: Gross interest income | B6: ='Track A · Pay-30'!B7+'Track B · BNPL'!B7+'Track C · Extension'!B7 -> 8.7546575 | C6: ='Track A · Pay-30'!C7+'Track B · BNPL'!C7+'Track C · Extension'!C7 -> 52.527945 | D6: ='Track A · Pay-30'!D7+'Track B · BNPL'!D7+'Track C · Extension'!D7 -> 140.07452 | E6: ='Track A · Pay-30'!E7+'Track B · BNPL'!E7+'Track C · Extension'!E7 -> 280.14904 | F6: ='Track A · Pay-30'!F7+'Track B · BNPL'!F7+'Track C · Extension'!F7 -> 455.24219
A7: Funding cost | B7: ='Track A · Pay-30'!B10+'Track B · BNPL'!B10+'Track C · Extension'!B10 -> 3.3056507 | C7: ='Track A · Pay-30'!C10+'Track B · BNPL'!C10+'Track C · Extension'!C10 -> 19.833904 | D7: ='Track A · Pay-30'!D10+'Track B · BNPL'!D10+'Track C · Extension'!D10 -> 52.890411 | E7: ='Track A · Pay-30'!E10+'Track B · BNPL'!E10+'Track C · Extension'!E10 -> 105.78082 | F7: ='Track A · Pay-30'!F10+'Track B · BNPL'!F10+'Track C · Extension'!F10 -> 171.89384
A8: NIM | B8: ='Track A · Pay-30'!B12+'Track B · BNPL'!B12+'Track C · Extension'!B12 -> 5.4490068 | C8: ='Track A · Pay-30'!C12+'Track B · BNPL'!C12+'Track C · Extension'!C12 -> 32.694041 | D8: ='Track A · Pay-30'!D12+'Track B · BNPL'!D12+'Track C · Extension'!D12 -> 87.18411 | E8: ='Track A · Pay-30'!E12+'Track B · BNPL'!E12+'Track C · Extension'!E12 -> 174.36822 | F8: ='Track A · Pay-30'!F12+'Track B · BNPL'!F12+'Track C · Extension'!F12 -> 283.34836
A9: Loss provision | B9: ='Track A · Pay-30'!B17+'Track B · BNPL'!B17+'Track C · Extension'!B17 -> 1.3555479 | C9: ='Track A · Pay-30'!C17+'Track B · BNPL'!C17+'Track C · Extension'!C17 -> 8.1332877 | D9: ='Track A · Pay-30'!D17+'Track B · BNPL'!D17+'Track C · Extension'!D17 -> 21.688767 | E9: ='Track A · Pay-30'!E17+'Track B · BNPL'!E17+'Track C · Extension'!E17 -> 43.377534 | F9: ='Track A · Pay-30'!F17+'Track B · BNPL'!F17+'Track C · Extension'!F17 -> 70.488493
A10: Risk-adj margin | B10: ='Track A · Pay-30'!B19+'Track B · BNPL'!B19+'Track C · Extension'!B19 -> 4.0934589 | C10: ='Track A · Pay-30'!C19+'Track B · BNPL'!C19+'Track C · Extension'!C19 -> 24.560753 | D10: ='Track A · Pay-30'!D19+'Track B · BNPL'!D19+'Track C · Extension'!D19 -> 65.495342 | E10: ='Track A · Pay-30'!E19+'Track B · BNPL'!E19+'Track C · Extension'!E19 -> 130.99068 | F10: ='Track A · Pay-30'!F19+'Track B · BNPL'!F19+'Track C · Extension'!F19 -> 212.85986
A11: OpEx | B11: ='Track A · Pay-30'!B22+'Track B · BNPL'!B22+'Track C · Extension'!B22 -> 2.0383151 | C11: ='Track A · Pay-30'!C22+'Track B · BNPL'!C22+'Track C · Extension'!C22 -> 9.1541096 | D11: ='Track A · Pay-30'!D22+'Track B · BNPL'!D22+'Track C · Extension'!D22 -> 19.528767 | E11: ='Track A · Pay-30'!E22+'Track B · BNPL'!E22+'Track C · Extension'!E22 -> 37.104658 | F11: ='Track A · Pay-30'!F22+'Track B · BNPL'!F22+'Track C · Extension'!F22 -> 58.391014
A12: Net contribution | B12: ='Track A · Pay-30'!B24+'Track B · BNPL'!B24+'Track C · Extension'!B24 -> 2.0551438 | C12: ='Track A · Pay-30'!C24+'Track B · BNPL'!C24+'Track C · Extension'!C24 -> 15.406644 | D12: ='Track A · Pay-30'!D24+'Track B · BNPL'!D24+'Track C · Extension'!D24 -> 45.966575 | E12: ='Track A · Pay-30'!E24+'Track B · BNPL'!E24+'Track C · Extension'!E24 -> 93.886027 | F12: ='Track A · Pay-30'!F24+'Track B · BNPL'!F24+'Track C · Extension'!F24 -> 154.46885
A13: Equity | B13: ='Track A · Pay-30'!B27+'Track B · BNPL'!B27+'Track C · Extension'!B27 -> 7.119863 | C13: ='Track A · Pay-30'!C27+'Track B · BNPL'!C27+'Track C · Extension'!C27 -> 42.719178 | D13: ='Track A · Pay-30'!D27+'Track B · BNPL'!D27+'Track C · Extension'!D27 -> 113.91781 | E13: ='Track A · Pay-30'!E27+'Track B · BNPL'!E27+'Track C · Extension'!E27 -> 227.83562 | F13: ='Track A · Pay-30'!F27+'Track B · BNPL'!F27+'Track C · Extension'!F27 -> 370.23288
A15: Ratios
A16: NIM (% of book) | B16: =B8/B5*100 -> 10.714545 | C16: =C8/C5*100 -> 10.714545 | D16: =D8/D5*100 -> 10.714545 | E16: =E8/E5*100 -> 10.714545 | F16: =F8/F5*100 -> 10.714545
A17: Loss rate (% of book) | B17: =B9/B5*100 -> 2.6654545 | C17: =C9/C5*100 -> 2.6654545 | D17: =D9/D5*100 -> 2.6654545 | E17: =E9/E5*100 -> 2.6654545 | F17: =F9/F5*100 -> 2.6654545
A18: OpEx (% of book) | B18: =B11/B5*100 -> 4.008 | C18: =C11/C5*100 -> 3 | D18: =D11/D5*100 -> 2.4 | E18: =E11/E5*100 -> 2.28 | F18: =F11/F5*100 -> 2.208
A19: Net margin (% of revenue) | B19: =IF(B6>0,B12/B6*100,0) -> 23.474863 | C19: =IF(C6>0,C12/C6*100,0) -> 29.330376 | D19: =IF(D6>0,D12/D6*100,0) -> 32.815801 | E19: =IF(E6>0,E12/E6*100,0) -> 33.512886 | F19: =IF(F6>0,F12/F6*100,0) -> 33.931136
A20: ROA (% of avg book) | B20: =B12/B5*100 -> 4.0410909 | C20: =C12/C5*100 -> 5.0490909 | D20: =D12/D5*100 -> 5.6490909 | E20: =E12/E5*100 -> 5.7690909 | F20: =F12/F5*100 -> 5.8410909
A21: RAROC (% on equity) | B21: =IF(B13>0,B12/B13*100,0) -> 28.864935 | C21: =IF(C13>0,C12/C13*100,0) -> 36.064935 | D21: =IF(D13>0,D12/D13*100,0) -> 40.350649 | E21: =IF(E13>0,E12/E13*100,0) -> 41.207792 | F21: =IF(F13>0,F12/F13*100,0) -> 41.722078
A23: Reconciliation to Reported Earnings
A24: Walks operating Net contribution to post-tax return on equity. Adds CAC, compliance overhead, write-off true-up, and UAE CIT (9%).
A26: Operating Net contribution (from row 12) | B26: =B12 -> 2.0551438 | C26: =C12 -> 15.406644 | D26: =D12 -> 45.966575 | E26: =E12 -> 93.886027 | F26: =F12 -> 154.46885
A28: (−) Customer acquisition cost | B28: =-'Volume & Mix'!B5*0.005 -> -1.25 | C28: =-'Volume & Mix'!C5*0.0035 -> -5.25 | D28: =-'Volume & Mix'!D5*0.002 -> -8 | E28: =-'Volume & Mix'!E5*0.0015 -> -12 | F28: =-'Volume & Mix'!F5*0.0012 -> -15.6
A29: (−) Compliance & regulatory overhead | B29: -3 | C29: -5 | D29: -7 | E29: -10 | F29: -12
A30: (−) Bad-debt write-off true-up | B30: =-B5*0.0025 -> -0.12714041 | C30: =-C5*0.0025 -> -0.76284247 | D30: =-D5*0.0025 -> -2.0342466 | E30: =-E5*0.0025 -> -4.0684932 | F30: =-F5*0.0025 -> -6.6113014
A32: Pre-tax income | B32: =SUM(B26:B30) -> -2.3219966 | C32: =SUM(C26:C30) -> 4.3938014 | D32: =SUM(D26:D30) -> 28.932329 | E32: =SUM(E26:E30) -> 67.817534 | F32: =SUM(F26:F30) -> 120.25755
A33: (−) UAE corporate tax (9%) | B33: =-MAX(0,B32)*0.09 -> 0 | C33: =-MAX(0,C32)*0.09 -> -0.39544212 | D33: =-MAX(0,D32)*0.09 -> -2.6039096 | E33: =-MAX(0,E32)*0.09 -> -6.1035781 | F33: =-MAX(0,F32)*0.09 -> -10.823179
A35: Net income to equity | B35: =B32+B33 -> -2.3219966 | C35: =C32+C33 -> 3.9983592 | D35: =D32+D33 -> 26.328419 | E35: =E32+E33 -> 61.713956 | F35: =F32+F33 -> 109.43437
A37: Post-tax ROA (% of avg book) | B37: =B35/B5*100 -> -4.5658114 | C37: =C35/C5*100 -> 1.3103489 | D37: =D35/D5*100 -> 3.2356475 | E37: =E35/E5*100 -> 3.7921875 | F37: =F35/F5*100 -> 4.1381554
A38: Post-tax RAROC (% on equity) | B38: =IF(B13>0,B35/B13*100,0) -> -32.612939 | C38: =IF(C13>0,C35/C13*100,0) -> 9.3596352 | D38: =IF(D13>0,D35/D13*100,0) -> 23.111768 | E38: =IF(E13>0,E35/E13*100,0) -> 27.087054 | F38: =IF(F13>0,F35/F13*100,0) -> 29.558253

Sheet Unit Economics
A1: Unit Economics — per AED 100k of Invoice Face Value
A2: Per-invoice contribution by track. Useful for pricing-committee debates.
A4: Line (AED per 100k) | B4: Pay-30 | C4: BNPL | D4: Extension
A5: Invoice face | B5: =100000 -> 100000 | C5: =100000 -> 100000 | D5: =100000 -> 100000
A6: Advanced principal | B6: =B5*advance_rate/100 -> 90000 | C6: =B5*advance_rate/100 -> 90000 | D6: =B5*advance_rate/100 -> 90000
A7: Tenor (days) | B7: =tenor_pay30 -> 30 | C7: =tenor_bnpl -> 105 | D7: =tenor_ext -> 180
A8: Yield (annual %) | B8: =fee_pay30_mo*12 -> 15.6 | C8: =fee_bnpl_mo*12 -> 18 | D8: =fee_ext_apr -> 16
A9: Gross fee earned | B9: =B6*B8/100*B7/365 -> 1153.9726 | C9: =C6*C8/100*C7/365 -> 4660.274 | D9: =D6*D8/100*D7/365 -> 7101.3699
A10: Funding cost | B10: =B6*cof_apr/100*B7/365 -> 480.82192 | C10: =C6*cof_apr/100*C7/365 -> 1682.8767 | D10: =D6*cof_apr/100*D7/365 -> 2884.9315
A11: NIM | B11: =B9-B10 -> 673.15068 | C11: =C9-C10 -> 2977.3973 | D11: =D9-D10 -> 4216.4384
A12: Expected loss | B12: =B6*pd_pay30/100*lgd_pay30/100*ead_pay30/100*B7/365 -> 51.780822 | C12: =C6*pd_bnpl/100*lgd_bnpl/100*ead_bnpl/100*C7/365 -> 466.0274 | D12: =D6*pd_ext/100*lgd_ext/100*ead_ext/100*D7/365 -> 2884.9315
A13: Risk-adj margin | B13: =B11-B12 -> 621.36986 | C13: =C11-C12 -> 2511.3699 | D13: =D11-D12 -> 1331.5068
A14: OpEx (mature, % of book) | B14: =B6*opex_pct/100*B7/365 -> 177.53425 | C14: =C6*opex_pct/100*C7/365 -> 621.36986 | D14: =D6*opex_pct/100*D7/365 -> 1065.2055
A15: Net contribution per invoice | B15: =B13-B14 -> 443.83562 | C15: =C13-C14 -> 1890 | D15: =D13-D14 -> 266.30137
A16: Net contribution as % of face | B16: =B15/B5*100 -> 0.44383562 | C16: =C15/C5*100 -> 1.89 | D16: =D15/D5*100 -> 0.26630137

Sheet Sensitivity
A1: Sensitivity · Y3 Net Contribution (AED M) vs PD Multiplier × Cost of Funds
A2: Holds all else constant. Useful for stress-test discussions with risk committee.
J3: PD mult → | K3: 0.6 | L3: 0.8 | M3: 1 | N3: 1.2 | O3: 1.5 | P3: 1.8 | Q3: 2.2
A4: PD × → / COF ↓ | B4: 0.6× PD | C4: 0.8× PD | D4: 1.0× PD | E4: 1.2× PD | F4: 1.5× PD | G4: 1.8× PD | H4: 2.2× PD | J4: COF ↓
A5: COF 5.5% | B5: =(disb_y3*advance_rate/100*tenor_pay30/365*mix_pay30/100)*(fee_pay30_mo*12/100-$J5-pd_pay30*K$3*lgd_pay30/100*ead_pay30/100/100-opex_pct*opex_y3_mult/100)+(disb_y3*advance_rate/100*tenor_bnpl/365*mix_bnpl/100)*(fee_bnpl_mo*12/100-$J5-pd_bnpl*K$3*lgd_bnpl/100*ead_bnpl/100/100-opex_pct*opex_y3_mult/100)+(disb_y3*advance_rate/100*tenor_ext/365*mix_ext/100)*(fee_ext_apr/100-$J5-pd_ext*K$3*lgd_ext/100*ead_ext/100/100-opex_pct*opex_y3_mult/100) -> 62.779068 | C5: =(disb_y3*advance_rate/100*tenor_pay30/365*mix_pay30/100)*(fee_pay30_mo*12/100-$J5-pd_pay30*L$3*lgd_pay30/100*ead_pay30/100/100-opex_pct*opex_y3_mult/100)+(disb_y3*advance_rate/100*tenor_bnpl/365*mix_bnpl/100)*(fee_bnpl_mo*12/100-$J5-pd_bnpl*L$3*lgd_bnpl/100*ead_bnpl/100/100-opex_pct*opex_y3_mult/100)+(disb_y3*advance_rate/100*tenor_ext/365*mix_ext/100)*(fee_ext_apr/100-$J5-pd_ext*L$3*lgd_ext/100*ead_ext/100/100-opex_pct*opex_y3_mult/100) -> 58.441315 | D5: =(disb_y3*advance_rate/100*tenor_pay30/365*mix_pay30/100)*(fee_pay30_mo*12/100-$J5-pd_pay30*M$3*lgd_pay30/100*ead_pay30/100/100-opex_pct*opex_y3_mult/100)+(disb_y3*advance_rate/100*tenor_bnpl/365*mix_bnpl/100)*(fee_bnpl_mo*12/100-$J5-pd_bnpl*M$3*lgd_bnpl/100*ead_bnpl/100/100-opex_pct*opex_y3_mult/100)+(disb_y3*advance_rate/100*tenor_ext/365*mix_ext/100)*(fee_ext_apr/100-$J5-pd_ext*M$3*lgd_ext/100*ead_ext/100/100-opex_pct*opex_y3_mult/100) -> 54.103562 | E5: =(disb_y3*advance_rate/100*tenor_pay30/365*mix_pay30/100)*(fee_pay30_mo*12/100-$J5-pd_pay30*N$3*lgd_pay30/100*ead_pay30/100/100-opex_pct*opex_y3_mult/100)+(disb_y3*advance_rate/100*tenor_bnpl/365*mix_bnpl/100)*(fee_bnpl_mo*12/100-$J5-pd_bnpl*N$3*lgd_bnpl/100*ead_bnpl/100/100-opex_pct*opex_y3_mult/100)+(disb_y3*advance_rate/100*tenor_ext/365*mix_ext/100)*(fee_ext_apr/100-$J5-pd_ext*N$3*lgd_ext/100*ead_ext/100/100-opex_pct*opex_y3_mult/100) -> 49.765808 | F5: =(disb_y3*advance_rate/100*tenor_pay30/365*mix_pay30/100)*(fee_pay30_mo*12/100-$J5-pd_pay30*O$3*lgd_pay30/100*ead_pay30/100/100-opex_pct*opex_y3_mult/100)+(disb_y3*advance_rate/100*tenor_bnpl/365*mix_bnpl/100)*(fee_bnpl_mo*12/100-$J5-pd_bnpl*O$3*lgd_bnpl/100*ead_bnpl/100/100-opex_pct*opex_y3_mult/100)+(disb_y3*advance_rate/100*tenor_ext/365*mix_ext/100)*(fee_ext_apr/100-$J5-pd_ext*O$3*lgd_ext/100*ead_ext/100/100-opex_pct*opex_y3_mult/100) -> 43.259178 | G5: =(disb_y3*advance_rate/100*tenor_pay30/365*mix_pay30/100)*(fee_pay30_mo*12/100-$J5-pd_pay30*P$3*lgd_pay30/100*ead_pay30/100/100-opex_pct*opex_y3_mult/100)+(disb_y3*advance_rate/100*tenor_bnpl/365*mix_bnpl/100)*(fee_bnpl_mo*12/100-$J5-pd_bnpl*P$3*lgd_bnpl/100*ead_bnpl/100/100-opex_pct*opex_y3_mult/100)+(disb_y3*advance_rate/100*tenor_ext/365*mix_ext/100)*(fee_ext_apr/100-$J5-pd_ext*P$3*lgd_ext/100*ead_ext/100/100-opex_pct*opex_y3_mult/100) -> 36.752548 | H5: =(disb_y3*advance_rate/100*tenor_pay30/365*mix_pay30/100)*(fee_pay30_mo*12/100-$J5-pd_pay30*Q$3*lgd_pay30/100*ead_pay30/100/100-opex_pct*opex_y3_mult/100)+(disb_y3*advance_rate/100*tenor_bnpl/365*mix_bnpl/100)*(fee_bnpl_mo*12/100-$J5-pd_bnpl*Q$3*lgd_bnpl/100*ead_bnpl/100/100-opex_pct*opex_y3_mult/100)+(disb_y3*advance_rate/100*tenor_ext/365*mix_ext/100)*(fee_ext_apr/100-$J5-pd_ext*Q$3*lgd_ext/100*ead_ext/100/100-opex_pct*opex_y3_mult/100) -> 28.077041 | J5: 0.055
A6: COF 6.0% | B6: =(disb_y3*advance_rate/100*tenor_pay30/365*mix_pay30/100)*(fee_pay30_mo*12/100-$J6-pd_pay30*K$3*lgd_pay30/100*ead_pay30/100/100-opex_pct*opex_y3_mult/100)+(disb_y3*advance_rate/100*tenor_bnpl/365*mix_bnpl/100)*(fee_bnpl_mo*12/100-$J6-pd_bnpl*K$3*lgd_bnpl/100*ead_bnpl/100/100-opex_pct*opex_y3_mult/100)+(disb_y3*advance_rate/100*tenor_ext/365*mix_ext/100)*(fee_ext_apr/100-$J6-pd_ext*K$3*lgd_ext/100*ead_ext/100/100-opex_pct*opex_y3_mult/100) -> 58.710575 | C6: =(disb_y3*advance_rate/100*tenor_pay30/365*mix_pay30/100)*(fee_pay30_mo*12/100-$J6-pd_pay30*L$3*lgd_pay30/100*ead_pay30/100/100-opex_pct*opex_y3_mult/100)+(disb_y3*advance_rate/100*tenor_bnpl/365*mix_bnpl/100)*(fee_bnpl_mo*12/100-$J6-pd_bnpl*L$3*lgd_bnpl/100*ead_bnpl/100/100-opex_pct*opex_y3_mult/100)+(disb_y3*advance_rate/100*tenor_ext/365*mix_ext/100)*(fee_ext_apr/100-$J6-pd_ext*L$3*lgd_ext/100*ead_ext/100/100-opex_pct*opex_y3_mult/100) -> 54.372822 | D6: =(disb_y3*advance_rate/100*tenor_pay30/365*mix_pay30/100)*(fee_pay30_mo*12/100-$J6-pd_pay30*M$3*lgd_pay30/100*ead_pay30/100/100-opex_pct*opex_y3_mult/100)+(disb_y3*advance_rate/100*tenor_bnpl/365*mix_bnpl/100)*(fee_bnpl_mo*12/100-$J6-pd_bnpl*M$3*lgd_bnpl/100*ead_bnpl/100/100-opex_pct*opex_y3_mult/100)+(disb_y3*advance_rate/100*tenor_ext/365*mix_ext/100)*(fee_ext_apr/100-$J6-pd_ext*M$3*lgd_ext/100*ead_ext/100/100-opex_pct*opex_y3_mult/100) -> 50.035068 | E6: =(disb_y3*advance_rate/100*tenor_pay30/365*mix_pay30/100)*(fee_pay30_mo*12/100-$J6-pd_pay30*N$3*lgd_pay30/100*ead_pay30/100/100-opex_pct*opex_y3_mult/100)+(disb_y3*advance_rate/100*tenor_bnpl/365*mix_bnpl/100)*(fee_bnpl_mo*12/100-$J6-pd_bnpl*N$3*lgd_bnpl/100*ead_bnpl/100/100-opex_pct*opex_y3_mult/100)+(disb_y3*advance_rate/100*tenor_ext/365*mix_ext/100)*(fee_ext_apr/100-$J6-pd_ext*N$3*lgd_ext/100*ead_ext/100/100-opex_pct*opex_y3_mult/100) -> 45.697315 | F6: =(disb_y3*advance_rate/100*tenor_pay30/365*mix_pay30/100)*(fee_pay30_mo*12/100-$J6-pd_pay30*O$3*lgd_pay30/100*ead_pay30/100/100-opex_pct*opex_y3_mult/100)+(disb_y3*advance_rate/100*tenor_bnpl/365*mix_bnpl/100)*(fee_bnpl_mo*12/100-$J6-pd_bnpl*O$3*lgd_bnpl/100*ead_bnpl/100/100-opex_pct*opex_y3_mult/100)+(disb_y3*advance_rate/100*tenor_ext/365*mix_ext/100)*(fee_ext_apr/100-$J6-pd_ext*O$3*lgd_ext/100*ead_ext/100/100-opex_pct*opex_y3_mult/100) -> 39.190685 | G6: =(disb_y3*advance_rate/100*tenor_pay30/365*mix_pay30/100)*(fee_pay30_mo*12/100-$J6-pd_pay30*P$3*lgd_pay30/100*ead_pay30/100/100-opex_pct*opex_y3_mult/100)+(disb_y3*advance_rate/100*tenor_bnpl/365*mix_bnpl/100)*(fee_bnpl_mo*12/100-$J6-pd_bnpl*P$3*lgd_bnpl/100*ead_bnpl/100/100-opex_pct*opex_y3_mult/100)+(disb_y3*advance_rate/100*tenor_ext/365*mix_ext/100)*(fee_ext_apr/100-$J6-pd_ext*P$3*lgd_ext/100*ead_ext/100/100-opex_pct*opex_y3_mult/100) -> 32.684055 | H6: =(disb_y3*advance_rate/100*tenor_pay30/365*mix_pay30/100)*(fee_pay30_mo*12/100-$J6-pd_pay30*Q$3*lgd_pay30/100*ead_pay30/100/100-opex_pct*opex_y3_mult/100)+(disb_y3*advance_rate/100*tenor_bnpl/365*mix_bnpl/100)*(fee_bnpl_mo*12/100-$J6-pd_bnpl*Q$3*lgd_bnpl/100*ead_bnpl/100/100-opex_pct*opex_y3_mult/100)+(disb_y3*advance_rate/100*tenor_ext/365*mix_ext/100)*(fee_ext_apr/100-$J6-pd_ext*Q$3*lgd_ext/100*ead_ext/100/100-opex_pct*opex_y3_mult/100) -> 24.008548 | J6: 0.06
A7: COF 6.5% | B7: =(disb_y3*advance_rate/100*tenor_pay30/365*mix_pay30/100)*(fee_pay30_mo*12/100-$J7-pd_pay30*K$3*lgd_pay30/100*ead_pay30/100/100-opex_pct*opex_y3_mult/100)+(disb_y3*advance_rate/100*tenor_bnpl/365*mix_bnpl/100)*(fee_bnpl_mo*12/100-$J7-pd_bnpl*K$3*lgd_bnpl/100*ead_bnpl/100/100-opex_pct*opex_y3_mult/100)+(disb_y3*advance_rate/100*tenor_ext/365*mix_ext/100)*(fee_ext_apr/100-$J7-pd_ext*K$3*lgd_ext/100*ead_ext/100/100-opex_pct*opex_y3_mult/100) -> 54.642082 | C7: =(disb_y3*advance_rate/100*tenor_pay30/365*mix_pay30/100)*(fee_pay30_mo*12/100-$J7-pd_pay30*L$3*lgd_pay30/100*ead_pay30/100/100-opex_pct*opex_y3_mult/100)+(disb_y3*advance_rate/100*tenor_bnpl/365*mix_bnpl/100)*(fee_bnpl_mo*12/100-$J7-pd_bnpl*L$3*lgd_bnpl/100*ead_bnpl/100/100-opex_pct*opex_y3_mult/100)+(disb_y3*advance_rate/100*tenor_ext/365*mix_ext/100)*(fee_ext_apr/100-$J7-pd_ext*L$3*lgd_ext/100*ead_ext/100/100-opex_pct*opex_y3_mult/100) -> 50.304329 | D7: =(disb_y3*advance_rate/100*tenor_pay30/365*mix_pay30/100)*(fee_pay30_mo*12/100-$J7-pd_pay30*M$3*lgd_pay30/100*ead_pay30/100/100-opex_pct*opex_y3_mult/100)+(disb_y3*advance_rate/100*tenor_bnpl/365*mix_bnpl/100)*(fee_bnpl_mo*12/100-$J7-pd_bnpl*M$3*lgd_bnpl/100*ead_bnpl/100/100-opex_pct*opex_y3_mult/100)+(disb_y3*advance_rate/100*tenor_ext/365*mix_ext/100)*(fee_ext_apr/100-$J7-pd_ext*M$3*lgd_ext/100*ead_ext/100/100-opex_pct*opex_y3_mult/100) -> 45.966575 | E7: =(disb_y3*advance_rate/100*tenor_pay30/365*mix_pay30/100)*(fee_pay30_mo*12/100-$J7-pd_pay30*N$3*lgd_pay30/100*ead_pay30/100/100-opex_pct*opex_y3_mult/100)+(disb_y3*advance_rate/100*tenor_bnpl/365*mix_bnpl/100)*(fee_bnpl_mo*12/100-$J7-pd_bnpl*N$3*lgd_bnpl/100*ead_bnpl/100/100-opex_pct*opex_y3_mult/100)+(disb_y3*advance_rate/100*tenor_ext/365*mix_ext/100)*(fee_ext_apr/100-$J7-pd_ext*N$3*lgd_ext/100*ead_ext/100/100-opex_pct*opex_y3_mult/100) -> 41.628822 | F7: =(disb_y3*advance_rate/100*tenor_pay30/365*mix_pay30/100)*(fee_pay30_mo*12/100-$J7-pd_pay30*O$3*lgd_pay30/100*ead_pay30/100/100-opex_pct*opex_y3_mult/100)+(disb_y3*advance_rate/100*tenor_bnpl/365*mix_bnpl/100)*(fee_bnpl_mo*12/100-$J7-pd_bnpl*O$3*lgd_bnpl/100*ead_bnpl/100/100-opex_pct*opex_y3_mult/100)+(disb_y3*advance_rate/100*tenor_ext/365*mix_ext/100)*(fee_ext_apr/100-$J7-pd_ext*O$3*lgd_ext/100*ead_ext/100/100-opex_pct*opex_y3_mult/100) -> 35.122192 | G7: =(disb_y3*advance_rate/100*tenor_pay30/365*mix_pay30/100)*(fee_pay30_mo*12/100-$J7-pd_pay30*P$3*lgd_pay30/100*ead_pay30/100/100-opex_pct*opex_y3_mult/100)+(disb_y3*advance_rate/100*tenor_bnpl/365*mix_bnpl/100)*(fee_bnpl_mo*12/100-$J7-pd_bnpl*P$3*lgd_bnpl/100*ead_bnpl/100/100-opex_pct*opex_y3_mult/100)+(disb_y3*advance_rate/100*tenor_ext/365*mix_ext/100)*(fee_ext_apr/100-$J7-pd_ext*P$3*lgd_ext/100*ead_ext/100/100-opex_pct*opex_y3_mult/100) -> 28.615562 | H7: =(disb_y3*advance_rate/100*tenor_pay30/365*mix_pay30/100)*(fee_pay30_mo*12/100-$J7-pd_pay30*Q$3*lgd_pay30/100*ead_pay30/100/100-opex_pct*opex_y3_mult/100)+(disb_y3*advance_rate/100*tenor_bnpl/365*mix_bnpl/100)*(fee_bnpl_mo*12/100-$J7-pd_bnpl*Q$3*lgd_bnpl/100*ead_bnpl/100/100-opex_pct*opex_y3_mult/100)+(disb_y3*advance_rate/100*tenor_ext/365*mix_ext/100)*(fee_ext_apr/100-$J7-pd_ext*Q$3*lgd_ext/100*ead_ext/100/100-opex_pct*opex_y3_mult/100) -> 19.940055 | J7: 0.065
A8: COF 7.0% | B8: =(disb_y3*advance_rate/100*tenor_pay30/365*mix_pay30/100)*(fee_pay30_mo*12/100-$J8-pd_pay30*K$3*lgd_pay30/100*ead_pay30/100/100-opex_pct*opex_y3_mult/100)+(disb_y3*advance_rate/100*tenor_bnpl/365*mix_bnpl/100)*(fee_bnpl_mo*12/100-$J8-pd_bnpl*K$3*lgd_bnpl/100*ead_bnpl/100/100-opex_pct*opex_y3_mult/100)+(disb_y3*advance_rate/100*tenor_ext/365*mix_ext/100)*(fee_ext_apr/100-$J8-pd_ext*K$3*lgd_ext/100*ead_ext/100/100-opex_pct*opex_y3_mult/100) -> 50.573589 | C8: =(disb_y3*advance_rate/100*tenor_pay30/365*mix_pay30/100)*(fee_pay30_mo*12/100-$J8-pd_pay30*L$3*lgd_pay30/100*ead_pay30/100/100-opex_pct*opex_y3_mult/100)+(disb_y3*advance_rate/100*tenor_bnpl/365*mix_bnpl/100)*(fee_bnpl_mo*12/100-$J8-pd_bnpl*L$3*lgd_bnpl/100*ead_bnpl/100/100-opex_pct*opex_y3_mult/100)+(disb_y3*advance_rate/100*tenor_ext/365*mix_ext/100)*(fee_ext_apr/100-$J8-pd_ext*L$3*lgd_ext/100*ead_ext/100/100-opex_pct*opex_y3_mult/100) -> 46.235836 | D8: =(disb_y3*advance_rate/100*tenor_pay30/365*mix_pay30/100)*(fee_pay30_mo*12/100-$J8-pd_pay30*M$3*lgd_pay30/100*ead_pay30/100/100-opex_pct*opex_y3_mult/100)+(disb_y3*advance_rate/100*tenor_bnpl/365*mix_bnpl/100)*(fee_bnpl_mo*12/100-$J8-pd_bnpl*M$3*lgd_bnpl/100*ead_bnpl/100/100-opex_pct*opex_y3_mult/100)+(disb_y3*advance_rate/100*tenor_ext/365*mix_ext/100)*(fee_ext_apr/100-$J8-pd_ext*M$3*lgd_ext/100*ead_ext/100/100-opex_pct*opex_y3_mult/100) -> 41.898082 | E8: =(disb_y3*advance_rate/100*tenor_pay30/365*mix_pay30/100)*(fee_pay30_mo*12/100-$J8-pd_pay30*N$3*lgd_pay30/100*ead_pay30/100/100-opex_pct*opex_y3_mult/100)+(disb_y3*advance_rate/100*tenor_bnpl/365*mix_bnpl/100)*(fee_bnpl_mo*12/100-$J8-pd_bnpl*N$3*lgd_bnpl/100*ead_bnpl/100/100-opex_pct*opex_y3_mult/100)+(disb_y3*advance_rate/100*tenor_ext/365*mix_ext/100)*(fee_ext_apr/100-$J8-pd_ext*N$3*lgd_ext/100*ead_ext/100/100-opex_pct*opex_y3_mult/100) -> 37.560329 | F8: =(disb_y3*advance_rate/100*tenor_pay30/365*mix_pay30/100)*(fee_pay30_mo*12/100-$J8-pd_pay30*O$3*lgd_pay30/100*ead_pay30/100/100-opex_pct*opex_y3_mult/100)+(disb_y3*advance_rate/100*tenor_bnpl/365*mix_bnpl/100)*(fee_bnpl_mo*12/100-$J8-pd_bnpl*O$3*lgd_bnpl/100*ead_bnpl/100/100-opex_pct*opex_y3_mult/100)+(disb_y3*advance_rate/100*tenor_ext/365*mix_ext/100)*(fee_ext_apr/100-$J8-pd_ext*O$3*lgd_ext/100*ead_ext/100/100-opex_pct*opex_y3_mult/100) -> 31.053699 | G8: =(disb_y3*advance_rate/100*tenor_pay30/365*mix_pay30/100)*(fee_pay30_mo*12/100-$J8-pd_pay30*P$3*lgd_pay30/100*ead_pay30/100/100-opex_pct*opex_y3_mult/100)+(disb_y3*advance_rate/100*tenor_bnpl/365*mix_bnpl/100)*(fee_bnpl_mo*12/100-$J8-pd_bnpl*P$3*lgd_bnpl/100*ead_bnpl/100/100-opex_pct*opex_y3_mult/100)+(disb_y3*advance_rate/100*tenor_ext/365*mix_ext/100)*(fee_ext_apr/100-$J8-pd_ext*P$3*lgd_ext/100*ead_ext/100/100-opex_pct*opex_y3_mult/100) -> 24.547068 | H8: =(disb_y3*advance_rate/100*tenor_pay30/365*mix_pay30/100)*(fee_pay30_mo*12/100-$J8-pd_pay30*Q$3*lgd_pay30/100*ead_pay30/100/100-opex_pct*opex_y3_mult/100)+(disb_y3*advance_rate/100*tenor_bnpl/365*mix_bnpl/100)*(fee_bnpl_mo*12/100-$J8-pd_bnpl*Q$3*lgd_bnpl/100*ead_bnpl/100/100-opex_pct*opex_y3_mult/100)+(disb_y3*advance_rate/100*tenor_ext/365*mix_ext/100)*(fee_ext_apr/100-$J8-pd_ext*Q$3*lgd_ext/100*ead_ext/100/100-opex_pct*opex_y3_mult/100) -> 15.871562 | J8: 0.07
A9: COF 7.5% | B9: =(disb_y3*advance_rate/100*tenor_pay30/365*mix_pay30/100)*(fee_pay30_mo*12/100-$J9-pd_pay30*K$3*lgd_pay30/100*ead_pay30/100/100-opex_pct*opex_y3_mult/100)+(disb_y3*advance_rate/100*tenor_bnpl/365*mix_bnpl/100)*(fee_bnpl_mo*12/100-$J9-pd_bnpl*K$3*lgd_bnpl/100*ead_bnpl/100/100-opex_pct*opex_y3_mult/100)+(disb_y3*advance_rate/100*tenor_ext/365*mix_ext/100)*(fee_ext_apr/100-$J9-pd_ext*K$3*lgd_ext/100*ead_ext/100/100-opex_pct*opex_y3_mult/100) -> 46.505096 | C9: =(disb_y3*advance_rate/100*tenor_pay30/365*mix_pay30/100)*(fee_pay30_mo*12/100-$J9-pd_pay30*L$3*lgd_pay30/100*ead_pay30/100/100-opex_pct*opex_y3_mult/100)+(disb_y3*advance_rate/100*tenor_bnpl/365*mix_bnpl/100)*(fee_bnpl_mo*12/100-$J9-pd_bnpl*L$3*lgd_bnpl/100*ead_bnpl/100/100-opex_pct*opex_y3_mult/100)+(disb_y3*advance_rate/100*tenor_ext/365*mix_ext/100)*(fee_ext_apr/100-$J9-pd_ext*L$3*lgd_ext/100*ead_ext/100/100-opex_pct*opex_y3_mult/100) -> 42.167342 | D9: =(disb_y3*advance_rate/100*tenor_pay30/365*mix_pay30/100)*(fee_pay30_mo*12/100-$J9-pd_pay30*M$3*lgd_pay30/100*ead_pay30/100/100-opex_pct*opex_y3_mult/100)+(disb_y3*advance_rate/100*tenor_bnpl/365*mix_bnpl/100)*(fee_bnpl_mo*12/100-$J9-pd_bnpl*M$3*lgd_bnpl/100*ead_bnpl/100/100-opex_pct*opex_y3_mult/100)+(disb_y3*advance_rate/100*tenor_ext/365*mix_ext/100)*(fee_ext_apr/100-$J9-pd_ext*M$3*lgd_ext/100*ead_ext/100/100-opex_pct*opex_y3_mult/100) -> 37.829589 | E9: =(disb_y3*advance_rate/100*tenor_pay30/365*mix_pay30/100)*(fee_pay30_mo*12/100-$J9-pd_pay30*N$3*lgd_pay30/100*ead_pay30/100/100-opex_pct*opex_y3_mult/100)+(disb_y3*advance_rate/100*tenor_bnpl/365*mix_bnpl/100)*(fee_bnpl_mo*12/100-$J9-pd_bnpl*N$3*lgd_bnpl/100*ead_bnpl/100/100-opex_pct*opex_y3_mult/100)+(disb_y3*advance_rate/100*tenor_ext/365*mix_ext/100)*(fee_ext_apr/100-$J9-pd_ext*N$3*lgd_ext/100*ead_ext/100/100-opex_pct*opex_y3_mult/100) -> 33.491836 | F9: =(disb_y3*advance_rate/100*tenor_pay30/365*mix_pay30/100)*(fee_pay30_mo*12/100-$J9-pd_pay30*O$3*lgd_pay30/100*ead_pay30/100/100-opex_pct*opex_y3_mult/100)+(disb_y3*advance_rate/100*tenor_bnpl/365*mix_bnpl/100)*(fee_bnpl_mo*12/100-$J9-pd_bnpl*O$3*lgd_bnpl/100*ead_bnpl/100/100-opex_pct*opex_y3_mult/100)+(disb_y3*advance_rate/100*tenor_ext/365*mix_ext/100)*(fee_ext_apr/100-$J9-pd_ext*O$3*lgd_ext/100*ead_ext/100/100-opex_pct*opex_y3_mult/100) -> 26.985205 | G9: =(disb_y3*advance_rate/100*tenor_pay30/365*mix_pay30/100)*(fee_pay30_mo*12/100-$J9-pd_pay30*P$3*lgd_pay30/100*ead_pay30/100/100-opex_pct*opex_y3_mult/100)+(disb_y3*advance_rate/100*tenor_bnpl/365*mix_bnpl/100)*(fee_bnpl_mo*12/100-$J9-pd_bnpl*P$3*lgd_bnpl/100*ead_bnpl/100/100-opex_pct*opex_y3_mult/100)+(disb_y3*advance_rate/100*tenor_ext/365*mix_ext/100)*(fee_ext_apr/100-$J9-pd_ext*P$3*lgd_ext/100*ead_ext/100/100-opex_pct*opex_y3_mult/100) -> 20.478575 | H9: =(disb_y3*advance_rate/100*tenor_pay30/365*mix_pay30/100)*(fee_pay30_mo*12/100-$J9-pd_pay30*Q$3*lgd_pay30/100*ead_pay30/100/100-opex_pct*opex_y3_mult/100)+(disb_y3*advance_rate/100*tenor_bnpl/365*mix_bnpl/100)*(fee_bnpl_mo*12/100-$J9-pd_bnpl*Q$3*lgd_bnpl/100*ead_bnpl/100/100-opex_pct*opex_y3_mult/100)+(disb_y3*advance_rate/100*tenor_ext/365*mix_ext/100)*(fee_ext_apr/100-$J9-pd_ext*Q$3*lgd_ext/100*ead_ext/100/100-opex_pct*opex_y3_mult/100) -> 11.803068 | J9: 0.075
A10: COF 8.0% | B10: =(disb_y3*advance_rate/100*tenor_pay30/365*mix_pay30/100)*(fee_pay30_mo*12/100-$J10-pd_pay30*K$3*lgd_pay30/100*ead_pay30/100/100-opex_pct*opex_y3_mult/100)+(disb_y3*advance_rate/100*tenor_bnpl/365*mix_bnpl/100)*(fee_bnpl_mo*12/100-$J10-pd_bnpl*K$3*lgd_bnpl/100*ead_bnpl/100/100-opex_pct*opex_y3_mult/100)+(disb_y3*advance_rate/100*tenor_ext/365*mix_ext/100)*(fee_ext_apr/100-$J10-pd_ext*K$3*lgd_ext/100*ead_ext/100/100-opex_pct*opex_y3_mult/100) -> 42.436603 | C10: =(disb_y3*advance_rate/100*tenor_pay30/365*mix_pay30/100)*(fee_pay30_mo*12/100-$J10-pd_pay30*L$3*lgd_pay30/100*ead_pay30/100/100-opex_pct*opex_y3_mult/100)+(disb_y3*advance_rate/100*tenor_bnpl/365*mix_bnpl/100)*(fee_bnpl_mo*12/100-$J10-pd_bnpl*L$3*lgd_bnpl/100*ead_bnpl/100/100-opex_pct*opex_y3_mult/100)+(disb_y3*advance_rate/100*tenor_ext/365*mix_ext/100)*(fee_ext_apr/100-$J10-pd_ext*L$3*lgd_ext/100*ead_ext/100/100-opex_pct*opex_y3_mult/100) -> 38.098849 | D10: =(disb_y3*advance_rate/100*tenor_pay30/365*mix_pay30/100)*(fee_pay30_mo*12/100-$J10-pd_pay30*M$3*lgd_pay30/100*ead_pay30/100/100-opex_pct*opex_y3_mult/100)+(disb_y3*advance_rate/100*tenor_bnpl/365*mix_bnpl/100)*(fee_bnpl_mo*12/100-$J10-pd_bnpl*M$3*lgd_bnpl/100*ead_bnpl/100/100-opex_pct*opex_y3_mult/100)+(disb_y3*advance_rate/100*tenor_ext/365*mix_ext/100)*(fee_ext_apr/100-$J10-pd_ext*M$3*lgd_ext/100*ead_ext/100/100-opex_pct*opex_y3_mult/100) -> 33.761096 | E10: =(disb_y3*advance_rate/100*tenor_pay30/365*mix_pay30/100)*(fee_pay30_mo*12/100-$J10-pd_pay30*N$3*lgd_pay30/100*ead_pay30/100/100-opex_pct*opex_y3_mult/100)+(disb_y3*advance_rate/100*tenor_bnpl/365*mix_bnpl/100)*(fee_bnpl_mo*12/100-$J10-pd_bnpl*N$3*lgd_bnpl/100*ead_bnpl/100/100-opex_pct*opex_y3_mult/100)+(disb_y3*advance_rate/100*tenor_ext/365*mix_ext/100)*(fee_ext_apr/100-$J10-pd_ext*N$3*lgd_ext/100*ead_ext/100/100-opex_pct*opex_y3_mult/100) -> 29.423342 | F10: =(disb_y3*advance_rate/100*tenor_pay30/365*mix_pay30/100)*(fee_pay30_mo*12/100-$J10-pd_pay30*O$3*lgd_pay30/100*ead_pay30/100/100-opex_pct*opex_y3_mult/100)+(disb_y3*advance_rate/100*tenor_bnpl/365*mix_bnpl/100)*(fee_bnpl_mo*12/100-$J10-pd_bnpl*O$3*lgd_bnpl/100*ead_bnpl/100/100-opex_pct*opex_y3_mult/100)+(disb_y3*advance_rate/100*tenor_ext/365*mix_ext/100)*(fee_ext_apr/100-$J10-pd_ext*O$3*lgd_ext/100*ead_ext/100/100-opex_pct*opex_y3_mult/100) -> 22.916712 | G10: =(disb_y3*advance_rate/100*tenor_pay30/365*mix_pay30/100)*(fee_pay30_mo*12/100-$J10-pd_pay30*P$3*lgd_pay30/100*ead_pay30/100/100-opex_pct*opex_y3_mult/100)+(disb_y3*advance_rate/100*tenor_bnpl/365*mix_bnpl/100)*(fee_bnpl_mo*12/100-$J10-pd_bnpl*P$3*lgd_bnpl/100*ead_bnpl/100/100-opex_pct*opex_y3_mult/100)+(disb_y3*advance_rate/100*tenor_ext/365*mix_ext/100)*(fee_ext_apr/100-$J10-pd_ext*P$3*lgd_ext/100*ead_ext/100/100-opex_pct*opex_y3_mult/100) -> 16.410082 | H10: =(disb_y3*advance_rate/100*tenor_pay30/365*mix_pay30/100)*(fee_pay30_mo*12/100-$J10-pd_pay30*Q$3*lgd_pay30/100*ead_pay30/100/100-opex_pct*opex_y3_mult/100)+(disb_y3*advance_rate/100*tenor_bnpl/365*mix_bnpl/100)*(fee_bnpl_mo*12/100-$J10-pd_bnpl*Q$3*lgd_bnpl/100*ead_bnpl/100/100-opex_pct*opex_y3_mult/100)+(disb_y3*advance_rate/100*tenor_ext/365*mix_ext/100)*(fee_ext_apr/100-$J10-pd_ext*Q$3*lgd_ext/100*ead_ext/100/100-opex_pct*opex_y3_mult/100) -> 7.7345753 | J10: 0.08
A11: COF 8.5% | B11: =(disb_y3*advance_rate/100*tenor_pay30/365*mix_pay30/100)*(fee_pay30_mo*12/100-$J11-pd_pay30*K$3*lgd_pay30/100*ead_pay30/100/100-opex_pct*opex_y3_mult/100)+(disb_y3*advance_rate/100*tenor_bnpl/365*mix_bnpl/100)*(fee_bnpl_mo*12/100-$J11-pd_bnpl*K$3*lgd_bnpl/100*ead_bnpl/100/100-opex_pct*opex_y3_mult/100)+(disb_y3*advance_rate/100*tenor_ext/365*mix_ext/100)*(fee_ext_apr/100-$J11-pd_ext*K$3*lgd_ext/100*ead_ext/100/100-opex_pct*opex_y3_mult/100) -> 38.36811 | C11: =(disb_y3*advance_rate/100*tenor_pay30/365*mix_pay30/100)*(fee_pay30_mo*12/100-$J11-pd_pay30*L$3*lgd_pay30/100*ead_pay30/100/100-opex_pct*opex_y3_mult/100)+(disb_y3*advance_rate/100*tenor_bnpl/365*mix_bnpl/100)*(fee_bnpl_mo*12/100-$J11-pd_bnpl*L$3*lgd_bnpl/100*ead_bnpl/100/100-opex_pct*opex_y3_mult/100)+(disb_y3*advance_rate/100*tenor_ext/365*mix_ext/100)*(fee_ext_apr/100-$J11-pd_ext*L$3*lgd_ext/100*ead_ext/100/100-opex_pct*opex_y3_mult/100) -> 34.030356 | D11: =(disb_y3*advance_rate/100*tenor_pay30/365*mix_pay30/100)*(fee_pay30_mo*12/100-$J11-pd_pay30*M$3*lgd_pay30/100*ead_pay30/100/100-opex_pct*opex_y3_mult/100)+(disb_y3*advance_rate/100*tenor_bnpl/365*mix_bnpl/100)*(fee_bnpl_mo*12/100-$J11-pd_bnpl*M$3*lgd_bnpl/100*ead_bnpl/100/100-opex_pct*opex_y3_mult/100)+(disb_y3*advance_rate/100*tenor_ext/365*mix_ext/100)*(fee_ext_apr/100-$J11-pd_ext*M$3*lgd_ext/100*ead_ext/100/100-opex_pct*opex_y3_mult/100) -> 29.692603 | E11: =(disb_y3*advance_rate/100*tenor_pay30/365*mix_pay30/100)*(fee_pay30_mo*12/100-$J11-pd_pay30*N$3*lgd_pay30/100*ead_pay30/100/100-opex_pct*opex_y3_mult/100)+(disb_y3*advance_rate/100*tenor_bnpl/365*mix_bnpl/100)*(fee_bnpl_mo*12/100-$J11-pd_bnpl*N$3*lgd_bnpl/100*ead_bnpl/100/100-opex_pct*opex_y3_mult/100)+(disb_y3*advance_rate/100*tenor_ext/365*mix_ext/100)*(fee_ext_apr/100-$J11-pd_ext*N$3*lgd_ext/100*ead_ext/100/100-opex_pct*opex_y3_mult/100) -> 25.354849 | F11: =(disb_y3*advance_rate/100*tenor_pay30/365*mix_pay30/100)*(fee_pay30_mo*12/100-$J11-pd_pay30*O$3*lgd_pay30/100*ead_pay30/100/100-opex_pct*opex_y3_mult/100)+(disb_y3*advance_rate/100*tenor_bnpl/365*mix_bnpl/100)*(fee_bnpl_mo*12/100-$J11-pd_bnpl*O$3*lgd_bnpl/100*ead_bnpl/100/100-opex_pct*opex_y3_mult/100)+(disb_y3*advance_rate/100*tenor_ext/365*mix_ext/100)*(fee_ext_apr/100-$J11-pd_ext*O$3*lgd_ext/100*ead_ext/100/100-opex_pct*opex_y3_mult/100) -> 18.848219 | G11: =(disb_y3*advance_rate/100*tenor_pay30/365*mix_pay30/100)*(fee_pay30_mo*12/100-$J11-pd_pay30*P$3*lgd_pay30/100*ead_pay30/100/100-opex_pct*opex_y3_mult/100)+(disb_y3*advance_rate/100*tenor_bnpl/365*mix_bnpl/100)*(fee_bnpl_mo*12/100-$J11-pd_bnpl*P$3*lgd_bnpl/100*ead_bnpl/100/100-opex_pct*opex_y3_mult/100)+(disb_y3*advance_rate/100*tenor_ext/365*mix_ext/100)*(fee_ext_apr/100-$J11-pd_ext*P$3*lgd_ext/100*ead_ext/100/100-opex_pct*opex_y3_mult/100) -> 12.341589 | H11: =(disb_y3*advance_rate/100*tenor_pay30/365*mix_pay30/100)*(fee_pay30_mo*12/100-$J11-pd_pay30*Q$3*lgd_pay30/100*ead_pay30/100/100-opex_pct*opex_y3_mult/100)+(disb_y3*advance_rate/100*tenor_bnpl/365*mix_bnpl/100)*(fee_bnpl_mo*12/100-$J11-pd_bnpl*Q$3*lgd_bnpl/100*ead_bnpl/100/100-opex_pct*opex_y3_mult/100)+(disb_y3*advance_rate/100*tenor_ext/365*mix_ext/100)*(fee_ext_apr/100-$J11-pd_ext*Q$3*lgd_ext/100*ead_ext/100/100-opex_pct*opex_y3_mult/100) -> 3.6660822 | J11: 0.085
A14: Read-out:
A15: Centre cell (1.0× PD, 6.5% COF) is the base case Y3 net contribution — ties to Combined P&L.
A16: Top-right (severe default + cheap funding) shows downside; bottom-left vice versa.
A17: If centre is positive but 1.5× PD row goes negative → book is risk-rate-elastic, tighten underwriting before scaling.

Sheet Capital Plan
A1: Capital Plan · Tier-1 adequacy & equity headroom
A2: Required equity = book × equity_pct (14%). RWA assumed 100% (Basel III standardised, NBFC unsecured → unrated SME).
A4: Line (AED M) | B4: Y1 | C4: Y2 | D4: Y3 | E4: Y4 | F4: Y5 | G4: Source / Note
A6: Avg book | B6: ='Combined P&L'!B5 -> 50.856164 | C6: ='Combined P&L'!C5 -> 305.13699 | D6: ='Combined P&L'!D5 -> 813.69863 | E6: ='Combined P&L'!E5 -> 1627.3973 | F6: ='Combined P&L'!F5 -> 2644.5205 | G6: = Combined P&L row 5
A7: Risk-weighted assets (100% RWA) | B7: =B6*1 -> 50.856164 | C7: =C6*1 -> 305.13699 | D7: =D6*1 -> 813.69863 | E7: =E6*1 -> 1627.3973 | F7: =F6*1 -> 2644.5205 | G7: Basel III standardised: unrated SME unsecured → 100%.
A9: Required equity (Tier-1) | B9: =B6*equity_pct/100 -> 7.119863 | C9: =C6*equity_pct/100 -> 42.719178 | D9: =D6*equity_pct/100 -> 113.91781 | E9: =E6*equity_pct/100 -> 227.83562 | F9: =F6*equity_pct/100 -> 370.23288 | G9: = book × equity_pct (14%). CBUAE Reg 32/2013 + 1-pt CRO management buffer above 13% standard.
A11: Equity raised in year (input) | B11: 110 | C11: 250 | D11: 0 | E11: 500 | F11: 0 | G11: Y1: seed 30 + Series A 80. Y2: Series B 250. Y4: Series C 500.
A12: Cumulative equity raised | B12: =B11 -> 110 | C12: =B12+C11 -> 360 | D12: =C12+D11 -> 360 | E12: =D12+E11 -> 860 | F12: =E12+F11 -> 860 | G12: Running sum of paid-in capital.
A14: Net contribution (annual) | B14: ='Combined P&L'!B12 -> 2.0551438 | C14: ='Combined P&L'!C12 -> 15.406644 | D14: ='Combined P&L'!D12 -> 45.966575 | E14: ='Combined P&L'!E12 -> 93.886027 | F14: ='Combined P&L'!F12 -> 154.46885 | G14: From Combined P&L row 12.
A15: Retained earnings (60% retention) | B15: =B14*0.6 -> 1.2330863 | C15: =B15+C14*0.6 -> 10.477073 | D15: =C15+D14*0.6 -> 38.057018 | E15: =D15+E14*0.6 -> 94.388634 | F15: =E15+F14*0.6 -> 187.06994 | G15: Cumulative retention; 40% paid as dividend / reinvestment buffer.
A17: Total available equity | B17: =B12+B15 -> 111.23309 | C17: =C12+C15 -> 370.47707 | D17: =D12+D15 -> 398.05702 | E17: =E12+E15 -> 954.38863 | F17: =F12+F15 -> 1047.0699 | G17: Cumulative paid-in + cumulative retained.
A19: Equity headroom (avail − required) | B19: =B17-B9 -> 104.11322 | C19: =C17-C9 -> 327.75789 | D19: =D17-D9 -> 284.13921 | E19: =E17-E9 -> 726.55302 | F19: =F17-F9 -> 676.83707 | G19: Negative → capital raise required to support book.
A21: Tier-1 ratio (avail / RWA) | B21: =B17/B7 -> 2.1872095 | C21: =C17/C7 -> 1.2141336 | D21: =D17/D7 -> 0.48919465 | E21: =E17/E7 -> 0.58645093 | F21: =F17/F7 -> 0.39593942 | G21: CBUAE min: 10.5% CET1 + 2.5% conservation = 13% standard.
A22: vs CBUAE 13% threshold | B22: =IF(B21>=0.13,"✓ PASS","✗ BREACH") -> ✓ PASS | C22: =IF(C21>=0.13,"✓ PASS","✗ BREACH") -> ✓ PASS | D22: =IF(D21>=0.13,"✓ PASS","✗ BREACH") -> ✓ PASS | E22: =IF(E21>=0.13,"✓ PASS","✗ BREACH") -> ✓ PASS | F22: =IF(F21>=0.13,"✓ PASS","✗ BREACH") -> ✓ PASS | G22: Hard floor; breach triggers regulatory capital action.

Sheet Funding Stack
A1: Funding Stack · blended cost of funds & covenant check
A2: Liability waterfall fundng total avg book. EIBOR base + spread per tranche. Tied to cof_apr in Inputs.
A4: Tranche assumptions | B4: Share % | C4: Spread bps | D4: EIBOR (base) | E4: All-in rate | F4: Source / Note
A5: Senior bank facility | B5: 0.76 | C5: 150 | D5: 0.052 | E5: =D5+C5/10000 -> 0.067 | F5: Mashreq / ENBD / FAB SCF lines. EIBOR + 150 bps. Senior share rebalanced to 76% (was 78%) so tranches sum to 100% with equity at 14%.
A6: Mezzanine / sub debt | B6: 0.1 | C6: 400 | D6: 0.052 | E6: =D6+C6/10000 -> 0.092 | F6: Family-office mezz / DFM-listed sukuk. EIBOR + 400 bps.
A7: Equity (Tier-1) | B7: =equity_pct/100 -> 0.14 | E7: 0 | F7: No interest cost. Equity return captured in RAROC.
A8: Total share | B8: =B5+B6+B7 -> 1 | F8: Should = 100%.
A10: Blended cost of funds (debt-only) | B10: =(B5*E5+B6*E6)/(B5+B6)*100 -> 6.9906977 | F10: Weighted across senior + mezz only. Compare to cof_apr (6.5%) on Inputs.
A11: vs cof_apr in Inputs | B11: =cof_apr -> 6.5 | F11: Hardcoded model assumption.
A12: Variance (bps) | B12: =(B10-B11)*100 -> 49.069767 | F12: Positive → Inputs cof_apr understates cost. Negative → buffer.
A13: Status | B13: =IF(B10<B11,"✓ Inputs conservative",IF(B10<=B11+50,"⚠ Within 50 bps","✗ Inputs cof_apr UNDERSTATES cost")) -> ⚠ Within 50 bps | F13: Decision rule for cof_apr update.
A15: Funding waterfall (AED M, Y3 base case) | B15: Y1 | C15: Y2 | D15: Y3 | E15: Y4 | F15: Y5
A16: Total avg book | B16: ='Combined P&L'!B5 -> 50.856164 | C16: ='Combined P&L'!C5 -> 305.13699 | D16: ='Combined P&L'!D5 -> 813.69863 | E16: ='Combined P&L'!E5 -> 1627.3973 | F16: ='Combined P&L'!F5 -> 2644.5205
A17: Senior facility drawn | B17: =B16*$B$5 -> 38.650685 | C17: =C16*$B$5 -> 231.90411 | D17: =D16*$B$5 -> 618.41096 | E17: =E16*$B$5 -> 1236.8219 | F17: =F16*$B$5 -> 2009.8356
A18: Mezzanine drawn | B18: =B16*$B$6 -> 5.0856164 | C18: =C16*$B$6 -> 30.513699 | D18: =D16*$B$6 -> 81.369863 | E18: =E16*$B$6 -> 162.73973 | F18: =F16*$B$6 -> 264.45205
A19: Equity funded | B19: =B16*$B$7 -> 7.119863 | C19: =C16*$B$7 -> 42.719178 | D19: =D16*$B$7 -> 113.91781 | E19: =E16*$B$7 -> 227.83562 | F19: =F16*$B$7 -> 370.23288
A21: Covenant tests
A22: Senior ≤ 85% of book | B22: =IF(B17/B16<=0.85,"✓ PASS","✗ BREACH") -> ✓ PASS | C22: =IF(C17/C16<=0.85,"✓ PASS","✗ BREACH") -> ✓ PASS | D22: =IF(D17/D16<=0.85,"✓ PASS","✗ BREACH") -> ✓ PASS | E22: =IF(E17/E16<=0.85,"✓ PASS","✗ BREACH") -> ✓ PASS | F22: =IF(F17/F16<=0.85,"✓ PASS","✗ BREACH") -> ✓ PASS
A23: Single-obligor ≤ 10% of book | B23: =IF(avg_ticket_k/1000/B16<=0.1,"✓ PASS","✗ BREACH") -> ✓ PASS | C23: =IF(avg_ticket_k/1000/C16<=0.1,"✓ PASS","✗ BREACH") -> ✓ PASS | D23: =IF(avg_ticket_k/1000/D16<=0.1,"✓ PASS","✗ BREACH") -> ✓ PASS | E23: =IF(avg_ticket_k/1000/E16<=0.1,"✓ PASS","✗ BREACH") -> ✓ PASS | F23: =IF(avg_ticket_k/1000/F16<=0.1,"✓ PASS","✗ BREACH") -> ✓ PASS
A24: Tier-1 ≥ 13% (CBUAE) | B24: =IF('Capital Plan'!B21>=0.13,"✓ PASS","✗ BREACH") -> ✓ PASS | C24: =IF('Capital Plan'!C21>=0.13,"✓ PASS","✗ BREACH") -> ✓ PASS | D24: =IF('Capital Plan'!D21>=0.13,"✓ PASS","✗ BREACH") -> ✓ PASS | E24: =IF('Capital Plan'!E21>=0.13,"✓ PASS","✗ BREACH") -> ✓ PASS | F24: =IF('Capital Plan'!F21>=0.13,"✓ PASS","✗ BREACH") -> ✓ PASS

Sheet Scenarios
A1: Active scenario: | B1: Base | C1: =MATCH(B1,C4:F4,0) -> 1 | D1: ← scenario index (1-4)
A2: Pick from dropdown. All Tracks, Combined P&L, Capital Plan, and Funding Stack recompute live.
A4: Input (named range) | B4: Active value | C4: Base | D4: Upside | E4: Downside | F4: Stress | G4: Adjustment logic / source
A5: disb_y3 (AED M) | B5: =CHOOSE($C$1,C5,D5,E5,F5) -> 4000 | C5: 4000 | D5: =C5*1.2 -> 4800 | E5: =C5*0.8 -> 3200 | F5: =C5*0.6 -> 2400 | G5: Up +20%, Down –20%, Stress –40% (CBUAE 2008/2020 SME originations contraction).
A6: fee_pay30_mo (%/mo) | B6: =CHOOSE($C$1,C6,D6,E6,F6) -> 1.3 | C6: 1.3 | D6: =C6+0.2 -> 1.5 | E6: =C6-0.2 -> 1.1 | F6: =C6 -> 1.3 | G6: Up/Down ±20 bps. Stress flat (price-takers in distress markets).
A7: fee_bnpl_mo (%/mo) | B7: =CHOOSE($C$1,C7,D7,E7,F7) -> 1.5 | C7: 1.5 | D7: =C7+0.2 -> 1.7 | E7: =C7-0.2 -> 1.3 | F7: =C7 -> 1.5 | G7: Same ±20 bps; stress flat.
A8: fee_ext_apr (% APR) | B8: =CHOOSE($C$1,C8,D8,E8,F8) -> 16 | C8: 16 | D8: =C8+2 -> 18 | E8: =C8-2 -> 14 | F8: =C8 -> 16 | G8: Up/Down ±200 bps; stress flat.
A9: cof_apr (% APR) | B9: =CHOOSE($C$1,C9,D9,E9,F9) -> 6.5 | C9: 6.5 | D9: =C9-0.5 -> 6 | E9: =C9+1 -> 7.5 | F9: =C9+2 -> 8.5 | G9: Stress +200 bps mirrors CBUAE 2020 EIBOR shock + 75 bps spread widening.
A10: pd_pay30 (% p.a.) | B10: =CHOOSE($C$1,C10,D10,E10,F10) -> 2 | C10: 2 | D10: =C10*0.8 -> 1.6 | E10: =C10*1.3 -> 2.6 | F10: =C10*1.8 -> 3.6 | G10: Up –20%, Down +30%, Stress +80% (CBUAE 2008 SME secured-factoring NPL spike: 2.0% → ~3.6%).
A11: pd_bnpl (% p.a.) | B11: =CHOOSE($C$1,C11,D11,E11,F11) -> 4 | C11: 4 | D11: =C11*0.8 -> 3.2 | E11: =C11*1.3 -> 5.2 | F11: =C11*1.8 -> 7.2 | G11: Same multipliers; CBUAE 2020 unsecured short-tenor cohort stress.
A12: pd_ext (% p.a.) | B12: =CHOOSE($C$1,C12,D12,E12,F12) -> 10 | C12: 10 | D12: =C12*0.8 -> 8 | E12: =C12*1.3 -> 13 | F12: =C12*1.8 -> 18 | G12: Workout cohort. Stress to 18% mirrors 2008 distressed bank-loan NPL ratios.
A13: opex_pct (% of book) | B13: =CHOOSE($C$1,C13,D13,E13,F13) -> 2.4 | C13: 2.4 | D13: =C13 -> 2.4 | E13: =C13 -> 2.4 | F13: =C13+0.5 -> 2.9 | G13: Stress +50 bps reflects collection-cost surge during distressed cohorts.
A16: Y3 KPI Panel — side-by-side (independent of dropdown)
A17: All 4 columns are computed inline from override values — they don't depend on B1.
A18: KPI | B18: (active) | C18: Base | D18: Upside | E18: Downside | F18: Stress
A19: Disbursement Y3 (AED M) | B19: =CHOOSE($C$1,C19,D19,E19,F19) -> 4000 | C19: =C5 -> 4000 | D19: =D5 -> 4800 | E19: =E5 -> 3200 | F19: =F5 -> 2400
A20: Pay-30 book Y3 (AED M) | B20: =CHOOSE($C$1,C20,D20,E20,F20) -> 118.35616 | C20: =C19*advance_rate/100*tenor_pay30/365*mix_pay30/100 -> 118.35616 | D20: =D19*advance_rate/100*tenor_pay30/365*mix_pay30/100 -> 142.0274 | E20: =E19*advance_rate/100*tenor_pay30/365*mix_pay30/100 -> 94.684932 | F20: =F19*advance_rate/100*tenor_pay30/365*mix_pay30/100 -> 71.013699
A21: BNPL book Y3 (AED M) | B21: =CHOOSE($C$1,C21,D21,E21,F21) -> 517.80822 | C21: =C19*advance_rate/100*tenor_bnpl/365*mix_bnpl/100 -> 517.80822 | D21: =D19*advance_rate/100*tenor_bnpl/365*mix_bnpl/100 -> 621.36986 | E21: =E19*advance_rate/100*tenor_bnpl/365*mix_bnpl/100 -> 414.24658 | F21: =F19*advance_rate/100*tenor_bnpl/365*mix_bnpl/100 -> 310.68493
A22: Extension book Y3 (AED M) | B22: =CHOOSE($C$1,C22,D22,E22,F22) -> 177.53425 | C22: =C19*advance_rate/100*tenor_ext/365*mix_ext/100 -> 177.53425 | D22: =D19*advance_rate/100*tenor_ext/365*mix_ext/100 -> 213.0411 | E22: =E19*advance_rate/100*tenor_ext/365*mix_ext/100 -> 142.0274 | F22: =F19*advance_rate/100*tenor_ext/365*mix_ext/100 -> 106.52055
A23: Total book Y3 (AED M) | B23: =CHOOSE($C$1,C23,D23,E23,F23) -> 813.69863 | C23: =C20+C21+C22 -> 813.69863 | D23: =D20+D21+D22 -> 976.43836 | E23: =E20+E21+E22 -> 650.9589 | F23: =F20+F21+F22 -> 488.21918
A25: Gross interest income Y3 (AED M) | B25: =CHOOSE($C$1,C25,D25,E25,F25) -> 140.07452 | C25: =C20*C6*12/100+C21*C7*12/100+C22*C8/100 -> 140.07452 | D25: =D20*D6*12/100+D21*D7*12/100+D22*D8/100 -> 190.67178 | E25: =E20*E6*12/100+E21*E7*12/100+E22*E8/100 -> 97.004712 | F25: =F20*F6*12/100+F21*F7*12/100+F22*F8/100 -> 84.044712
A26: Funding cost Y3 (AED M) | B26: =CHOOSE($C$1,C26,D26,E26,F26) -> 52.890411 | C26: =C23*C9/100 -> 52.890411 | D26: =D23*D9/100 -> 58.586301 | E26: =E23*E9/100 -> 48.821918 | F26: =F23*F9/100 -> 41.49863
A27: NIM Y3 (AED M) | B27: =CHOOSE($C$1,C27,D27,E27,F27) -> 87.18411 | C27: =C25-C26 -> 87.18411 | D27: =D25-D26 -> 132.08548 | E27: =E25-E26 -> 48.182795 | F27: =F25-F26 -> 42.546082
A28: Loss provision Y3 (AED M) | B28: =CHOOSE($C$1,C28,D28,E28,F28) -> 21.688767 | C28: =C20*C10*lgd_pay30/10000+C21*C11*lgd_bnpl/10000+C22*C12*lgd_ext/10000 -> 21.688767 | D28: =D20*D10*lgd_pay30/10000+D21*D11*lgd_bnpl/10000+D22*D12*lgd_ext/10000 -> 20.821216 | E28: =E20*E10*lgd_pay30/10000+E21*E11*lgd_bnpl/10000+E22*E12*lgd_ext/10000 -> 22.556318 | F28: =F20*F10*lgd_pay30/10000+F21*F11*lgd_bnpl/10000+F22*F12*lgd_ext/10000 -> 23.423868
A29: OpEx Y3 (AED M) | B29: =CHOOSE($C$1,C29,D29,E29,F29) -> 19.528767 | C29: =C23*C13*opex_y3_mult/100 -> 19.528767 | D29: =D23*D13*opex_y3_mult/100 -> 23.434521 | E29: =E23*E13*opex_y3_mult/100 -> 15.623014 | F29: =F23*F13*opex_y3_mult/100 -> 14.158356
A30: Net contribution Y3 (AED M) | B30: =CHOOSE($C$1,C30,D30,E30,F30) -> 45.966575 | C30: =C27-C28-C29 -> 45.966575 | D30: =D27-D28-D29 -> 87.829742 | E30: =E27-E28-E29 -> 10.003463 | F30: =F27-F28-F29 -> 4.9638575
A31: ROA Y3 (% of book) | B31: =CHOOSE($C$1,C31,D31,E31,F31) -> 0.056490909 | C31: =C30/C23 -> 0.056490909 | D31: =D30/D23 -> 0.089949091 | E31: =E30/E23 -> 0.015367273 | F31: =F30/F23 -> 0.010167273
A32: Equity required (14% of book) | B32: =CHOOSE($C$1,C32,D32,E32,F32) -> 113.91781 | C32: =C23*equity_pct/100 -> 113.91781 | D32: =D23*equity_pct/100 -> 136.70137 | E32: =E23*equity_pct/100 -> 91.134247 | F32: =F23*equity_pct/100 -> 68.350685
A33: RAROC Y3 (% on equity) | B33: =CHOOSE($C$1,C33,D33,E33,F33) -> 0.40350649 | C33: =IF(C32>0,C30/C32,0) -> 0.40350649 | D33: =IF(D32>0,D30/D32,0) -> 0.64249351 | E33: =IF(E32>0,E30/E32,0) -> 0.10976623 | F33: =IF(F32>0,F30/F32,0) -> 0.072623377

Sheet Break-even
A1: Break-even · Y2 disbursement & Y3 PD-stress tolerance
A2: Algebraic solutions — no Goal Seek required. Recompute live as named-range inputs change.
A4: [1] Y2 disbursement break-even (NetContrib ≥ fixed OpEx floor)
A6: Fixed OpEx floor Y2 (AED M) | B6: 8 | C6: Headcount + tech + regulatory minimum infrastructure run-rate Y2.
A8: Book per AED 1 of disbursement (factor) | B8: =advance_rate/100*(mix_pay30/100*tenor_pay30+mix_bnpl/100*tenor_bnpl+mix_ext/100*tenor_ext)/365 -> 0.20342466 | C8: = adv × Σ(mix×tenor) / 365. Approx 0.20 — each AED 1 disbursed sits ~73 days on avg.
A10: Per-track yield (% APR) | B10: Pay-30 | C10: BNPL | D10: Extension | E10: Weighted (% APR)
A11: Yield | B11: =fee_pay30_mo*12 -> 15.6 | C11: =fee_bnpl_mo*12 -> 18 | D11: =fee_ext_apr -> 16 | E11: =B11*(mix_pay30/100*tenor_pay30/(mix_pay30/100*tenor_pay30+mix_bnpl/100*tenor_bnpl+mix_ext/100*tenor_ext))+C11*(mix_bnpl/100*tenor_bnpl/(mix_pay30/100*tenor_pay30+mix_bnpl/100*tenor_bnpl+mix_ext/100*tenor_ext))+D11*(mix_ext/100*tenor_ext/(mix_pay30/100*tenor_pay30+mix_bnpl/100*tenor_bnpl+mix_ext/100*tenor_ext)) -> 17.214545
A12: Net loss rate (% of book) | B12: =pd_pay30*lgd_pay30/100 -> 0.7 | C12: =pd_bnpl*lgd_bnpl/100 -> 1.8 | D12: =pd_ext*lgd_ext/100 -> 6.5 | E12: =B12*(mix_pay30/100*tenor_pay30/(mix_pay30/100*tenor_pay30+mix_bnpl/100*tenor_bnpl+mix_ext/100*tenor_ext))+C12*(mix_bnpl/100*tenor_bnpl/(mix_pay30/100*tenor_pay30+mix_bnpl/100*tenor_bnpl+mix_ext/100*tenor_ext))+D12*(mix_ext/100*tenor_ext/(mix_pay30/100*tenor_pay30+mix_bnpl/100*tenor_bnpl+mix_ext/100*tenor_ext)) -> 2.6654545
A14: Variable margin (% of book) | B14: =E11-cof_apr-E12-opex_pct*opex_y2_mult -> 5.0490909 | C14: = weighted yield − COF − loss rate − OpEx Y2
A16: Variable margin per AED disbursed (factor) | B16: =B8*B14/100 -> 0.010271096 | C16: = book/disb factor × variable margin %
A18: Y2 disbursement break-even (AED M) | B18: =B6/B16 -> 778.88475 | C18: = OpEx floor / margin per AED disbursed
A19: vs current disb_y2 | B19: =disb_y2 -> 1500 | C19: Strategy doc plan.
A20: Headroom (current − BE) | B20: =B19-B18 -> 721.11525 | C20: Positive → plan covers fixed OpEx with margin to spare.
A21: Status | B21: =IF(B20>0,"✓ PASS — "&TEXT(B20/B18,"0%")&" headroom","✗ BREACH — disb_y2 below break-even") -> ✓ PASS — 93% headroom
A24: [2] Y3 PD-stress tolerance (PD multiplier where Y3 ROA = target)
A26: Target ROA Y3 (% of book) | B26: 5 | C26: Below this Y3 ROA, the book stops earning enough to compound.
A28: Y3 baseline weighted yield (% of book) | B28: =E11 -> 17.214545 | C28: From row 11 above.
A29: Y3 OpEx (% of book) | B29: =opex_pct*opex_y3_mult -> 2.4 | C29: = opex_pct × Y3 multiplier (mature).
A30: Y3 NIM after COF (% of book) | B30: =B28-cof_apr -> 10.714545 | C30: = weighted yield − COF.
A31: Baseline net loss rate at PD×1.0 (% of book) | B31: =E12 -> 2.6654545 | C31: From row 12 above.
A33: Allowable loss rate at target ROA (% of book) | B33: =B30-B29-B26 -> 3.3145455 | C33: = NIM − OpEx − ROA target. Loss budget.
A34: Implied PD multiplier | B34: =IF(B31>0,B33/B31,0) -> 1.2435198 | C34: Multiplier on all PDs that pushes Y3 ROA exactly to target. >1 = headroom; <1 = base case already breaches.
A35: Equivalent to PD shift | B35: =IF(B34>=1,"PDs can rise "&TEXT(B34-1,"0%")&" before ROA hits "&B26&"%","PDs must FALL "&TEXT(1-B34,"0%")&" to reach ROA "&B26&"%") -> PDs can rise 24% before ROA hits 5%
A36: vs Stress scenario (PD×1.8) | B36: =IF(B34>=1.8,"✓ Tolerates Stress — still earns ≥"&B26&"% ROA",IF(B34>=1.5,"⚠ Below Stress; tolerates 1.5× PD","✗ Below 1.5× PD — risk-rate elastic")) -> ✗ Below 1.5× PD — risk-rate elastic
A37: vs Downside scenario (PD×1.3) | B37: =IF(B34>=1.3,"✓ Tolerates Downside","✗ Below Downside multiplier") -> ✗ Below Downside multiplier

Sheet Vintage Cohorts
A1: Vintage Cohorts · Cumulative loss curves M0–M24
A2: Each Y1/Y2/Y3 cohort treated as a closed-end origination. Lifetime loss = Σ(mix × tenor × PD × LGD)/365 of advanced principal. Timing: 30% by M6, 80% by M18, 100% by M24.
A4: Loss timing curve (cumulative % of lifetime loss)
A5: Milestone | B5: M6 | C5: M12 | D5: M18 | E5: M24 | F5: Source / Note
A6: Cumulative % | B6: 0.3 | C6: 0.55 | D6: 0.8 | E6: 1 | F6: Lognormal: 30% in M0–6, 50% in M7–18, 20% in M19–24. Tail-heavier than retail; matches UAE SME workout norms.
A7: Period bucket | B7: M0–M6 | C7: M7–M12 | D7: M13–M18 | E7: M19–M24
A9: Per-cohort lifetime loss (% of advanced principal)
A10: Cohort | B10: Disbursed (AED M) | C10: Advanced (AED M) | D10: Lifetime loss % | E10: Lifetime loss (AED M) | F10: Decomposition
A11: Y1 vintage | B11: =disb_y1 -> 250 | C11: =B11*advance_rate/100 -> 225 | D11: =(mix_pay30/100*tenor_pay30*pd_pay30*lgd_pay30+mix_bnpl/100*tenor_bnpl*pd_bnpl*lgd_bnpl+mix_ext/100*tenor_ext*pd_ext*lgd_ext)/365/100 -> 0.60246575 | E11: =C11*D11/100 -> 1.3555479 | F11: = weighted PD×LGD scaled by tenor/365 (annualised → lifetime per cohort)
A12: Y2 vintage | B12: =disb_y2 -> 1500 | C12: =B12*advance_rate/100 -> 1350 | D12: =D11 -> 0.60246575 | E12: =C12*D12/100 -> 8.1332877 | F12: Same risk profile as Y1 (mix/PD/LGD unchanged)
A13: Y3 vintage | B13: =disb_y3 -> 4000 | C13: =B13*advance_rate/100 -> 3600 | D13: =D11 -> 0.60246575 | E13: =C13*D13/100 -> 21.688767 | F13: Same risk profile as Y1
A14: Total advanced (Y1+Y2+Y3) | C14: =C11+C12+C13 -> 5175
A15: Total lifetime loss | E15: =E11+E12+E13 -> 31.177603
A18: Cumulative loss schedule (% of advanced principal)
A19: Months on book →
A20: Months on book → | B20: M0 | C20: M1 | D20: M2 | E20: M3 | F20: M4 | G20: M5 | H20: M6 | I20: M7 | J20: M8 | K20: M9 | L20: M10 | M20: M11 | N20: M12 | O20: M13 | P20: M14 | Q20: M15 | R20: M16 | S20: M17 | T20: M18 | U20: M19 | V20: M20 | W20: M21 | X20: M22 | Y20: M23 | Z20: M24
A21: Cumulative % of lifetime loss | B21: =0 -> 0 | C21: =$B$6*1/6 -> 0.05 | D21: =$B$6*2/6 -> 0.1 | E21: =$B$6*3/6 -> 0.15 | F21: =$B$6*4/6 -> 0.2 | G21: =$B$6*5/6 -> 0.25 | H21: =$B$6*6/6 -> 0.3 | I21: =$B$6+($C$6-$B$6)*(7-6)/6 -> 0.34166667 | J21: =$B$6+($C$6-$B$6)*(8-6)/6 -> 0.38333333 | K21: =$B$6+($C$6-$B$6)*(9-6)/6 -> 0.425 | L21: =$B$6+($C$6-$B$6)*(10-6)/6 -> 0.46666667 | M21: =$B$6+($C$6-$B$6)*(11-6)/6 -> 0.50833333 | N21: =$B$6+($C$6-$B$6)*(12-6)/6 -> 0.55 | O21: =$C$6+($D$6-$C$6)*(13-12)/6 -> 0.59166667 | P21: =$C$6+($D$6-$C$6)*(14-12)/6 -> 0.63333333 | Q21: =$C$6+($D$6-$C$6)*(15-12)/6 -> 0.675 | R21: =$C$6+($D$6-$C$6)*(16-12)/6 -> 0.71666667 | S21: =$C$6+($D$6-$C$6)*(17-12)/6 -> 0.75833333 | T21: =$C$6+($D$6-$C$6)*(18-12)/6 -> 0.8 | U21: =$D$6+($E$6-$D$6)*(19-18)/6 -> 0.83333333 | V21: =$D$6+($E$6-$D$6)*(20-18)/6 -> 0.86666667 | W21: =$D$6+($E$6-$D$6)*(21-18)/6 -> 0.9 | X21: =$D$6+($E$6-$D$6)*(22-18)/6 -> 0.93333333 | Y21: =$D$6+($E$6-$D$6)*(23-18)/6 -> 0.96666667 | Z21: =$D$6+($E$6-$D$6)*(24-18)/6 -> 1
A22: Y1 vintage cum loss % | B22: =$D$11*B21/100 -> 0 | C22: =$D$11*C21/100 -> 0.00030123288 | D22: =$D$11*D21/100 -> 0.00060246575 | E22: =$D$11*E21/100 -> 0.00090369863 | F22: =$D$11*F21/100 -> 0.0012049315 | G22: =$D$11*G21/100 -> 0.0015061644 | H22: =$D$11*H21/100 -> 0.0018073973 | I22: =$D$11*I21/100 -> 0.0020584247 | ... Z22: =$D$11*Z21/100 -> 0.0060246575
A23: Y2 vintage cum loss % | B23: =$D$12*B21/100 -> 0 | C23: =$D$12*C21/100 -> 0.00030123288 | D23: =$D$12*D21/100 -> 0.00060246575 | E23: =$D$12*E21/100 -> 0.00090369863 | F23: =$D$12*F21/100 -> 0.0012049315 | G23: =$D$12*G21/100 -> 0.0015061644 | H23: =$D$12*H21/100 -> 0.0018073973 | I23: =$D$12*I21/100 -> 0.0020584247 | ... Z23: =$D$12*Z21/100 -> 0.0060246575
A24: Y3 vintage cum loss % | B24: =$D$13*B21/100 -> 0 | C24: =$D$13*C21/100 -> 0.00030123288 | D24: =$D$13*D21/100 -> 0.00060246575 | E24: =$D$13*E21/100 -> 0.00090369863 | F24: =$D$13*F21/100 -> 0.0012049315 | G24: =$D$13*G21/100 -> 0.0015061644 | H24: =$D$13*H21/100 -> 0.0018073973 | I24: =$D$13*I21/100 -> 0.0020584247 | ... Z24: =$D$13*Z21/100 -> 0.0060246575
A26: Y1 vintage cum loss (AED M) | B26: =$E$11*B21 -> 0 | C26: =$E$11*C21 -> 0.067777397 | D26: =$E$11*D21 -> 0.13555479 | E26: =$E$11*E21 -> 0.20333219 | F26: =$E$11*F21 -> 0.27110959 | G26: =$E$11*G21 -> 0.33888699 | H26: =$E$11*H21 -> 0.40666438 | I26: =$E$11*I21 -> 0.46314555 | ... Z26: =$E$11*Z21 -> 1.3555479
A27: Y2 vintage cum loss (AED M) | B27: =$E$12*B21 -> 0 | C27: =$E$12*C21 -> 0.40666438 | D27: =$E$12*D21 -> 0.81332877 | E27: =$E$12*E21 -> 1.2199932 | F27: =$E$12*F21 -> 1.6266575 | G27: =$E$12*G21 -> 2.0333219 | H27: =$E$12*H21 -> 2.4399863 | I27: =$E$12*I21 -> 2.7788733 | ... Z27: =$E$12*Z21 -> 8.1332877
A28: Y3 vintage cum loss (AED M) | B28: =$E$13*B21 -> 0 | C28: =$E$13*C21 -> 1.0844384 | D28: =$E$13*D21 -> 2.1688767 | E28: =$E$13*E21 -> 3.2533151 | F28: =$E$13*F21 -> 4.3377534 | G28: =$E$13*G21 -> 5.4221918 | H28: =$E$13*H21 -> 6.5066301 | I28: =$E$13*I21 -> 7.4103288 | ... Z28: =$E$13*Z21 -> 21.688767
A30: Portfolio cumulative loss (AED M) | B30: =B26+B27+B28 -> 0 | C30: =C26+C27+C28 -> 1.5588801 | D30: =D26+D27+D28 -> 3.1177603 | E30: =E26+E27+E28 -> 4.6766404 | F30: =F26+F27+F28 -> 6.2355205 | G30: =G26+G27+G28 -> 7.7944007 | H30: =H26+H27+H28 -> 9.3532808 | I30: =I26+I27+I28 -> 10.652348 | ... Z30: =Z26+Z27+Z28 -> 31.177603

Sheet Validation & Sources
A1: Validation against UAE benchmarks · Alternative scenarios
A4: Assumption | B4: Mal value | C4: Mkt range | D4: Source / risk-priced alternative
A5: Cost of funds | B5: 6.5% APR | C5: 6.0–8.0% | D5: 3M EIBOR ~5.2% + NBFI spread 1.0–1.5%. CBUAE Monetary Bulletin Q1 2026; Fitch UAE Banks 2026 outlook.
A6: Pay-30 discount fee | B6: 1.3%/mo | C6: 1.5–2.2%/mo | D6: Below market band intentionally — embedded-checkout convenience premium without consumer-style pricing on SME book. Mashreq SCF / CBI Trade band 1.5-2.2%.
A7: BNPL fee | B7: 1.5%/mo | C7: 2.0–2.8%/mo | D7: Below band — supplier-discount blend reflects embedded-platform play vs standalone B2B BNPL. Tightened from 1.8% to make headline RAROC defensible.
A8: Term Extension APR | B8: 16% APR | C8: 16–22% APR | D8: LOW END. Risk-priced alt: 19% APR. Test in Sensitivity sheet by editing fee_ext_apr.
A9: Pay-30 PD | B9: 0.02 | C9: 1.5–3.0% | D9: Invoice-secured factoring. CBUAE FSR 2025 §3.4 SME secured band.
A10: BNPL PD | B10: 0.04 | C10: 3.0–5.0% | D10: Multi-installment exposure. CBUAE FSR 2025 + Moody's UAE Banking 2026.
A11: Term Extension PD | B11: 0.1 | C11: 8.0–12.0% | D11: Distressed/workout cohort. CBUAE downturn template suggests 1.5× stress to 15%.
A12: Pay-30 LGD | B12: 0.35 | C12: 30–40% | D12: Tightened from 25% — Basel III IRB foundation 25% requires collateral perfection Mal won't have in Y1-Y3. Realistic UAE invoice-discount LGD 30-40% accounting for fraud, payor disputes, 90d collection lag.
A13: BNPL LGD | B13: 0.45 | C13: 40–55% | D13: Partial collateral via invoice; multi-installment dilutes recovery. Moody's UAE Banking 2026.
A14: Term Extension LGD | B14: 0.65 | C14: 55–75% | D14: Unsecured workout. CBUAE distressed-credit norms; FSRA NBFC reviews.
A15: EAD (all tracks) | B15: 1 | C15: 95–100% | D15: Full advanced principal at risk; no undrawn commitment. Basel III standardised approach.
A16: OpEx (mature) | B16: 2.4% of book | C16: 1.5–3.0% | D16: Reem Finance, Aafaq public filings. Y3 mature target; ramps from 4.0% Y1.
A17: Equity % | B17: 14% of book | C17: 10–15% | D17: Tightened from 12% — CBUAE Reg 32/2013: 13% standard (10.5% CET1 + 2.5% conservation buffer). Mal at 14% adds 1-pt CRO management buffer above standard.
A18: Advance rate | B18: 90% | C18: 80–95% | D18: Prime-obligor norm. Anchor-validated invoices can go 95%.
A19: Avg ticket | B19: AED 80k | C19: 50–120k | D19: UAE SME invoice median (DED registry inferred).
A21: Open validation tasks
A23: 1. Replace estimated UAE SME default sub-segment numbers with sector-specific ratios from IBISWorld connector once Cowork access is wired.
A24: 2. Replace blended PD/LGD with Moody's MCP private-company curves for actual UAE rating distribution.
A25: 3. Validate Pay-30 vs BNPL mix ratio against actual buyer-plan-picker telemetry once the prototype goes live to test users.
A26: 4. Stress-test extension cohort PD at 15% (1.5× base of 10%) — CBUAE downturn-shock template.
A27: 5. Cross-check OpEx ramp against actual cost-to-income ratios in audited financials of Reem Finance / Aafaq Islamic Finance.
A28: 6. Confirm 90% advance rate is acceptable to senior bank funding lines (Mashreq, ENBD): typical co-fund advance covenant 85%.
A29: 7. RAROC defensibility check: post-tax RAROC must land in 18-30% band to clear UAE NBFC peer comparison and credit committee review. Operating RAROC pre-overhead-and-tax may be higher; show both.
